Workbook

Sheet Реестр рисков
A1: Реестр рисков проекта Stud Book
A3: Название проекта | D3: Stud Book | E3: Версия | H3: 1.0
A4: Менеджер проекта | D4: Лопатин Даниил Игоревич | E4: Дата версии | H4: 17.10.2026
A5: Спонсор проекта | D5: Дасти Кроуфорд | E5: Статус-дата базового плана | H5: 17.10.2026
A6: Фаза проекта | D6: 3 — базовый план (вариант Б) | E6: Плановое окончание | H6: 26.12.2026 (закрытие до 31.12.2026)
A8: № | B8: Категория | C8: Риск | D8: Причина и событие | E8: Последствия для проекта | F8: Источник (ЗС) | G8: Пакеты ИСР, требования | H8: Признак наступления | I8: P (1–5) | J8: I (1–5) | K8: Балл P×I | L8: Приоритет | M8: Стратегия | N8: Превентивные меры | O8: План Б (при наступлении) | P8: Владелец | Q8: Когда контролировать | R8: Статус | S8: Дата выявления | T8: Ранг
A9: Р1 | B9: Требования и содержание | C9: Неполные и меняющиеся требования | D9: Заказчик не специалист в ИТ и описывает проблемы, а не решения; допущения А-5, А-7, А-8, А-12…А-14 имеют статус «подтвердить». На демонстрациях заказчик уточняет или меняет уже согласованное поведение экранов. | E9: Переделка экранов и логики (2.3, 3.1–3.5, 5.1), рост трудоёмкости, расход запаса расписания 5,1 раб. дн, частичная приёмка вехи. | F9: С-01, С-02, С-03 | G9: 2.1, 2.3, 3.1–3.5, 5.1; Т-01…Т-15 | H9: К 31.10 не подтверждены допущения со статусом «подтвердить»; на демонстрации больше 2 замечаний, меняющих согласованное поведение; запрос на изменение больше 8 ч. | I9: 4 | J9: 3 | K9: =I9*J9 -> 12 | L9: =IF(K9>=Методика!$C$21,"Высокий",IF(K9>=Методика!$C$22,"Средний","Низкий")) -> Высокий | M9: Снижение | N9: Подтвердить допущения на интервью в нулевом спринте (до 31.10); показывать макеты экранов (2.3) до разработки пакета; приоритизация MoSCoW и story map в фазе 4; все изменения — через журнал изменений с оценкой в часах. | O9: Изменения до 8 ч без влияния на Must принимает РП (п. 4.2 устава); крупнее — запрос на изменение с пересчётом плана и выводом равного объёма Should по согласованию с Дасти; остальное — в бэклог после проекта. | P9: Паноченко В.В. | Q9: 31.10; далее на каждой демонстрации | R9: Открыт | S9: 02.10.2026 | T9: =RANK(K9,$K$9:$K$25,0)+COUNTIF($K$9:K9,K9)-1 -> 3
A10: Р2 | B10: Предметная область | C10: Правила совместимости и готовности кобылы получены поздно или неверно | D10: Таблицу правил (А-9) предоставляет заказчик при участии ветеринара до 14.11.2026; ветеринар — внешняя сторона, сведения идут через Дасти. Правила могут прийти позже или с ошибками. | E10: Задержка 4.1 и 4.2 (4.2 входит в критическую цепочку расписания), переделка проверки пар, не выполняется критерий приёмки 7. | F10: С-01, С-07 | G10: 4.1, 4.2; Т-07; критерий 7 | H10: К 06.11 (плановое окончание 4.1) таблица правил не получена или не согласована; в правилах нет порогов (степень родства, сроки готовности). | I10: 3 | J10: 3 | K10: =I10*J10 -> 9 | L10: =IF(K10>=Методика!$C$21,"Высокий",IF(K10>=Методика!$C$22,"Средний","Низкий")) -> Средний | M10: Снижение | N10: Отправить заказчику шаблон таблицы правил с примерами в начале 4.1 (29.10); напомнить за неделю до срока; согласовать пороги на интервью; пять недопустимых и три допустимые контрольные пары включить в демоданные (2.5). | O10: По А-9 — рабочий набор правил команды (родство до 2-го поколения, занятость жеребца, отметка готовности) с пометкой «не подтверждено заказчиком». Правила хранятся таблицей, замена не требует переделки 4.2. | P10: Лопатин Д.И. | Q10: 29.10 (запрос); 06.11; 14.11 | R10: Открыт | S10: 02.10.2026 | T10: =RANK(K10,$K$9:$K$25,0)+COUNTIF($K$9:K10,K10)-1 -> 8
A11: Р3 | B11: Требования и содержание | C11: Недостаточно данных для справок, не определено понятие «контакт» | D11: Справки ядра (Т-03, Т-04) зависят от определения «контакта» (А-7) и состава записей размещения (А-8); оба допущения не подтверждены. Демоданные могут не покрывать сценарии справок. | E11: Справки — ядро продукта (Ц1, Must): переделка 3.4, 3.5 и демоданных, не проходят критерии 3–4. | F11: С-08, С-09, С-01 | G11: 2.5, 3.2, 3.4, 3.5; Т-03, Т-04; критерии 3–4 | H11: А-7, А-8 не подтверждены к 31.10; при тестировании (6.2) справка за период пустая или неполная; заказчик называет другие признаки контакта. | I11: 2 | J11: 4 | K11: =I11*J11 -> 8 | L11: =IF(K11>=Методика!$C$21,"Высокий",IF(K11>=Методика!$C$22,"Средний","Низкий")) -> Средний | M11: Снижение | N11: Подтвердить А-7, А-8 на интервью нулевого спринта; строить демоданные (2.5) от сценариев справок: не менее 25 записей размещения, контрольные случаи контактов; тест-кейсы справок — до начала 3.4 и 3.5. | O11: Зафиксировать определение А-7 как рабочее в журнале изменений; сделать тип контакта (случка / совместное размещение) фильтром справки, чтобы новое определение добавлялось без переделки; дополнить демоданные силами аналитика и тестировщика. | P11: Паноченко В.В. | Q11: 31.10; 03.11 (конец 2.5); 03.12 | R11: Открыт | S11: 02.10.2026 | T11: =RANK(K11,$K$9:$K$25,0)+COUNTIF($K$9:K11,K11)-1 -> 11
A12: Р4 | B12: Регуляторные | C12: Поля реестра не соответствуют требованиям породной ассоциации и учёта поголовья | D12: Состав полей реестра (Т-01) строится по описаниям заказчика; юридическая проверка норм штата Техас и ассоциации в проект не входит (п. 2.3 устава). | E12: Доработка карточки лошади и заглушки обмена с ассоциацией (6.1), повторный показ на следующей вехе. | F12: С-06, С-08 | G12: 3.1, 6.1; Т-01; критерий 1 | H12: На В1 (14.11) заказчик называет недостающие поля; ассоциация или регулятор требует иной формат данных (через заказчика). | I12: 2 | J12: 2 | K12: =I12*J12 -> 4 | L12: =IF(K12>=Методика!$C$21,"Высокий",IF(K12>=Методика!$C$22,"Средний","Низкий")) -> Низкий | M12: Передача | N12: Ответственность за состав полей несёт заказчик: список полей карточки утверждается Дасти до начала 3.1 (05.11). Родословная хранится в расширяемой структуре. | O12: Недостающие поля в пределах 8 ч добавляются решением РП (п. 4.2 устава) в ближайшей итерации; больше — запрос на изменение. | P12: Паноченко В.В. | Q12: 05.11; 14.11 (В1) | R12: Открыт | S12: 02.10.2026 | T12: =RANK(K12,$K$9:$K$25,0)+COUNTIF($K$9:K12,K12)-1 -> 14
A13: Р5 | B13: Сроки | C13: Срыв финальной приёмки 26.12.2026 | D13: Заказчику нужна работающая система к сезону (начало февраля), поэтому финальная приёмка 26.12 жёсткая. По расписанию (вариант Б) приёмка 6.3 заканчивается 18.12, запас 5,1 раб. дн, P(успеть) = 96%. Критическая цепочка: 2.2 → 2.5 → 3.1 → 3.2 → 3.5 → 4.2 → 6.3. | E13: Не выполняются Ц6–Ц7, удерживается платёж В4 (30%), досдача в резерве до 31.12 или за пределами семестра. | F13: С-01 | G13: 2.2, 2.5, 3.1, 3.2, 3.5, 4.2, 6.3 | H13: Отставание пакета критической цепочки больше 2 раб. дн; до 07.12 израсходовано больше половины запаса (2,5 раб. дн); SV < −10% на вехе. | I13: 2 | J13: 5 | K13: =I13*J13 -> 10 | L13: =IF(K13>=Методика!$C$21,"Высокий",IF(K13>=Методика!$C$22,"Средний","Низкий")) -> Средний | M13: Снижение | N13: Еженедельно сверять старт и финиш пакетов цепочки с расписанием; запас 5,1 раб. дн не тратить на некритичные работы; исполнители цепочки (Горбов, Кодинцев) не берут задачи вне цепочки; прогон по чек-листу до 6.3. | O13: По согласованию с Дасти урезать 5.1 (Should) — Паноченко и Нгуен помогают в 3.5 и 4.2; замечания приёмки досдать в резерве до 31.12 (п. 3.1 устава); сдвиг вехи — только с согласия заказчика и куратора. | P13: Лопатин Д.И. | Q13: Еженедельно; вехи В1–В4 | R13: Открыт | S13: 02.10.2026 | T13: =RANK(K13,$K$9:$K$25,0)+COUNTIF($K$9:K13,K13)-1 -> 7
A14: Р6 | B14: Требования и содержание | C14: Расширение ожиданий за границы проекта («система на вырост») | D14: Внешние стороны подталкивают заказчика к функциям вне границ п. 2.3: складской учёт и заказы поставщикам, автоматическая отправка данных страховщикам и регуляторам, реальные интеграции. | E14: Незапланированная работа, вытеснение Must-пакетов, срыв вех. | F14: С-01, С-08, С-09, С-11 | G14: 5.4, 6.1; Т-05, Т-12 | H14: Запросы, выходящие за п. 2.3 устава («а ещё пусть система сама…»); запрос на изменение без указания, что убрать из объёма. | I14: 3 | J14: 3 | K14: =I14*J14 -> 9 | L14: =IF(K14>=Методика!$C$21,"Высокий",IF(K14>=Методика!$C$22,"Средний","Низкий")) -> Средний | M14: Уклонение | N14: Границы закреплены в п. 2.3 и подписаны заказчиком. На каждой демонстрации сверять запросы с п. 2.3; любой запрос — в журнал изменений с оценкой в часах и влиянием на вехи; напоминать о позиции заказчика «не система на вырост». | O14: Принять изменение только с выводом равного объёма Should/Could и согласием Дасти (свыше 8 ч); крупные функции — отдельной договорённостью после проекта (как мобильное приложение, А-17). | P14: Лопатин Д.И. | Q14: При каждом запросе на изменение | R14: Открыт | S14: 02.10.2026 | T14: =RANK(K14,$K$9:$K$25,0)+COUNTIF($K$9:K14,K14)-1 -> 9
A15: Р7 | B15: Ресурсы (команда) | C15: Нехватка времени участников из-за учёбы | D15: Фонд времени ограничен учебной нагрузкой; базовый план требует 68 ч/нед (+2 ч каждому). Ноябрь–декабрь — контрольные и зачётная неделя, возможны болезни. | E15: Недоработка часов в пакетах, сдвиг критической цепочки, неравномерный вклад участников. | F15: С-05 | G15: Все пакеты 2.2–6.4 | H15: Фактические часы участника в трекере ниже 80% плана две недели подряд; задача «В процессе» дольше плановой длительности; участник предупреждает о сессии или болезни. | I15: 4 | J15: 4 | K15: =I15*J15 -> 16 | L15: =IF(K15>=Методика!$C$21,"Высокий",IF(K15>=Методика!$C$22,"Средний","Низкий")) -> Высокий | M15: Снижение | N15: План с загрузкой 63–81% фонда (запас); еженедельная сверка часов в трекере; заранее собрать график зачётов и учесть при планировании итераций 3–4; пары взаимозамены: Кодинцев ↔ Нгуен, Паноченко ↔ Шунулин. | O15: РП перераспределяет до 10% трудоёмкости между пакетами итерации (п. 4.2 устава); выбывшего заменяет напарник; при долгом выбытии — урезание 5.1 по согласованию и сообщение куратору. | P15: Лопатин Д.И. | Q15: Еженедельно; особо 07.12–25.12 | R15: Открыт | S15: 02.10.2026 | T15: =RANK(K15,$K$9:$K$25,0)+COUNTIF($K$9:K15,K15)-1 -> 1
A16: Р8 | B16: Стоимость | C16: Превышение плановой трудоёмкости и стоимости | D16: Оценки сделаны до опыта работы с инструментами; фактические часы могут превысить E по PERT. Стоимость варианта Б — 34 706 USD, с резервом 10% — 38 177 USD, потолок — 50 000 USD. | E16: CV < 0, рост EAC; при выходе за 38 177 USD — расход запаса до потолка по согласованию с заказчиком; нарушение Ц7 (отклонения не более 10%). | F16: С-05, С-01 | G16: Все пакеты; Ц7 | H16: На вехе CPI < 0,9 или CV < −10%; фактические часы пакета превысили пессимистическую оценку P; EAC > 38 177 USD. | I16: 3 | J16: 4 | K16: =I16*J16 -> 12 | L16: =IF(K16>=Методика!$C$21,"Высокий",IF(K16>=Методика!$C$22,"Средний","Низкий")) -> Высокий | M16: Принятие (активное) | N16: Резерв на риски 10% от стоимости; учёт фактических часов по каждой задаче; расчёт CV, SV, EAC на каждой вехе; пересмотр оценок оставшихся пакетов по фактической velocity после итерации 1. | O16: РП расходует резерв в пределах полномочий п. 4.2 устава; сверх лимитов — согласование с Дасти и Тэмми; при прогнозе выхода за потолок — урезание Should. | P16: Лопатин Д.И. | Q16: На каждой вехе (В1–В4) | R16: Открыт | S16: 02.10.2026 | T16: =RANK(K16,$K$9:$K$25,0)+COUNTIF($K$9:K16,K16)-1 -> 4
A17: Р9 | B17: Предметная область | C17: Задержка или пропуски данных ветеринара | D17: Ветеринар приходящий, записи о готовности и состоянии вносит Дасти по его сведениям (А-10). Сведения для правил готовности и сценариев ввода записей приходят с задержкой или неполными. | E17: Неполные правила готовности (критерий 7), неточный сценарий ввода записей (3.3). | F17: С-07, С-01, С-04 | G17: 3.3, 4.1; Т-06 | H17: К 06.11 нет сведений о признаках готовности кобылы; Дасти сообщает, что ветеринар недоступен. | I17: 2 | J17: 2 | K17: =I17*J17 -> 4 | L17: =IF(K17>=Методика!$C$21,"Высокий",IF(K17>=Методика!$C$22,"Средний","Низкий")) -> Низкий | M17: Принятие (активное) | N17: Демоданные вымышленные (А-16) и не зависят от реальных записей ветеринара; форма ввода — не более 7 полей и 3 шагов (критерий 6); вопросы к ветеринару передавать через Дасти одним списком. | O17: Рабочие правила готовности команды (А-9) с пометкой; уточнения ветеринара — в следующей итерации как малое изменение. | P17: Паноченко В.В. | Q17: 06.11; В2 | R17: Открыт | S17: 02.10.2026 | T17: =RANK(K17,$K$9:$K$25,0)+COUNTIF($K$9:K17,K17)-1 -> 15
A18: Р10 | B18: Организационные | C18: Разногласия по приёмке | D18: Критерии чек-листа трактуются заказчиком и командой по-разному. После запроса на изменение № 1 критерии 8 и 11 уточняются, 9 и 10 снимаются — возможна путаница. | E18: Частичная приёмка вехи и оплата доли, повторная доработка, конфликт с заказчиком. | F18: С-01, С-02 | G18: 6.3; чек-лист п. 2.4 устава | H18: На демонстрации критерий Must не принят или оспорен; замечание приёмки без опоры на критерии; заказчик ожидает функцию, снятую запросом на изменение № 1. | I18: 3 | J18: 4 | K18: =I18*J18 -> 12 | L18: =IF(K18>=Методика!$C$21,"Высокий",IF(K18>=Методика!$C$22,"Средний","Низкий")) -> Высокий | M18: Снижение; при споре — эскалация | N18: Тестировщик прогоняет чек-лист вехи за 2 дня до пары; уточнённую редакцию чек-листа (после ЗИ № 1) согласовать с Дасти письменно; решение по каждому критерию фиксировать в GitHub Issues. | O18: Эскалация куратору (Золотухин Р.О.); частичная приёмка с оплатой доли по принятым Must (п. 2.4 устава), доработка и повторная проверка до следующей пары. | P18: Сибирко И.С. | Q18: За 2 дня до каждой пары | R18: Открыт | S18: 02.10.2026 | T18: =RANK(K18,$K$9:$K$25,0)+COUNTIF($K$9:K18,K18)-1 -> 5
A19: Р11 | B19: Организационные | C19: Запрос на изменение № 1 не согласован | D19: Базовый план (вариант Б) опирается на ЗИ № 1: +2 ч/нед каждому и исключение 4.3, 5.2, 5.3, 5.4. Заказчик может не согласиться на потерю счетов (Ц5) и очереди (Ц4), куратор или участники — на рост часов. | E19: При 54 ч/нед даже Must + 5.1 заканчиваются 13.01.2027; полный объём не укладывается в срок даже при 82 ч/нед (окончание 29.12.2026). | F19: С-01, С-02, С-05, куратор | G19: 4.3, 5.1–5.4; Ц4, Ц5; критерии 8–11 | H19: На паре 17.10 ЗИ № 1 отклонён полностью или частично; заказчик требует вернуть счета или очередь; участник не может дать +2 ч/нед. | I19: 3 | J19: 5 | K19: =I19*J19 -> 15 | L19: =IF(K19>=Методика!$C$21,"Высокий",IF(K19>=Методика!$C$22,"Средний","Низкий")) -> Высокий | M19: Снижение | N19: Показать расчёт сценариев (книга «Сетевой график и PERT», лист «Сценарии») и вероятности срока; дать заказчику выбор: 5.1 (роль клиента) или 4.3 (очередь) — с тем же сроком; до пары подтвердить у каждого участника +2 ч/нед. | O19: Если заказчик выбирает 4.3 — сценарий «Must + 4.3 вместо 5.1» (окончание 18.12, но без роли клиента в Ц6). Если +2 ч/нед не согласованы — часть экранов (5.1, 4.2) понизить до кликабельного макета по согласованию с заказчиком и куратором. Счета (5.3) — первыми в бэклог после проекта. | P19: Лопатин Д.И. | Q19: 17.10 (пара фазы 3) | R19: Ожидает решения | S19: 17.10.2026 | T19: =RANK(K19,$K$9:$K$25,0)+COUNTIF($K$9:K19,K19)-1 -> 2
A20: Р12 | B20: Ресурсы (команда) | C20: Один разработчик серверной части на критической цепочке | D20: Серверная логика, API и БД (2.2, 3.1, 3.2, 3.5, 4.2) — у Горбова Н.В. (8 ч/нед в плане); в ноябре–декабре его загрузка 100%. Участника с теми же навыками в команде нет. | E20: Любое выбытие или задержка сдвигает критическую цепочку и финальную приёмку. | F20: С-05 | G20: 2.2, 3.1, 3.2, 3.5, 4.2 | H20: Задача серверной части просрочена больше чем на 2 раб. дня; Горбов недоступен больше 3 раб. дней; рост числа дефектов серверной части в 6.2. | I20: 3 | J20: 4 | K20: =I20*J20 -> 12 | L20: =IF(K20>=Методика!$C$21,"Высокий",IF(K20>=Методика!$C$22,"Средний","Низкий")) -> Высокий | M20: Снижение | N20: Схему БД и API описывать в репозитории по ходу 2.2; использовать готовый бэкенд-сервис (Supabase / PocketBase), чтобы сократить собственный код; Паноченко делает ревью кода и умеет развернуть стенд. | O20: Часть серверной логики переносится в готовый сервис или low-code; Паноченко или Нгуен подключаются к задачам бэкенда с генерацией кода LLM; при долгом выбытии — урезание 5.1 и сообщение куратору. | P20: Горбов Н.В. | Q20: Еженедельно, 19.10–16.12 | R20: Открыт | S20: 17.10.2026 | T20: =RANK(K20,$K$9:$K$25,0)+COUNTIF($K$9:K20,K20)-1 -> 6
... A25: Р17 | B25: Рыночные (бизнес) | C25: Конкуренты запускают удобную онлайн-запись | D25: У соседних ранчо уже есть онлайн-запись. Уход клиентов может заставить заказчика срочно поднять приоритет кабинета клиента и заказа семени (5.1, 5.2). | E25: Запрос на изменение приоритетов в итерациях 3–4, возврат 5.2 в объём. | F25: С-10, С-03 | G25: 5.1, 5.2; Т-09 | H25: Дасти сообщает об уходе клиентов к соседям или просит вернуть заказ семени с доставкой. | I25: 2 | J25: 2 | K25: =I25*J25 -> 4 | L25: =IF(K25>=Методика!$C$21,"Высокий",IF(K25>=Методика!$C$22,"Средний","Низкий")) -> Низкий | M25: Принятие (активное) | N25: 5.1 сохранён в базовом плане; 5.2 — первый кандидат на возврат при освободившемся ресурсе; в 5.1 заложить поле «тип услуги» для будущего заказа семени. | O25: Возврат 5.2 запросом на изменение взамен равного объёма; при нехватке ресурса — в бэклог после проекта. | P25: Нгуен Д.В. | Q25: На каждой демонстрации | R25: Открыт | S25: 17.10.2026 | T25: =RANK(K25,$K$9:$K$25,0)+COUNTIF($K$9:K25,K25)-1 -> 17
A27: Итого рисков | D27: =COUNTA(A9:A25) -> 17
A28: Высокий | D28: =COUNTIF(L9:L25,"Высокий") -> 6
A29: Средний | D29: =COUNTIF(L9:L25,"Средний") -> 7
A30: Низкий | D30: =COUNTIF(L9:L25,"Низкий") -> 4
A32: Р1–Р10 — риски из устава (п. 1.5), номера сохранены; Р11–Р17 выявлены при составлении базового плана (фаза 3). Источники — номера сторон из реестра заинтересованных сторон. P и I — по шкалам листа «Методика», балл и приоритет считаются формулами. Ранг — место по баллу (при равенстве — по номеру). Синий шрифт — входные значения.

Sheet Матрица
A1: Матрица вероятности и влияния
A2: В ячейке — номера рисков с такими P и I (формулы по листу «Реестр рисков»). Цвет зоны: красный — высокий приоритет (балл ≥ 12), жёлтый — средний (6–11), зелёный — низкий (≤ 5).
A4: Вероятность ↓ / Влияние → | C4: 1 — незначит. | D4: 2 — малое | E4: 3 — умеренное | F4: 4 — значит. | G4: 5 — критич. | I4: Рейтинг рисков по баллу
A5: 5 | B5: очень высокая | C5: =TRIM(IF(AND('Реестр рисков'!$I$9=5,'Реестр рисков'!$J$9=1),'Реестр рисков'!$A$9&" ","")&IF(AND('Реестр рисков'!$I$10=5,'Реестр рисков'!$J$10=1),'Реестр рисков'!$A$10&" ","")&IF(AND('Реестр рисков'!$I$11=5,'Реестр рисков'!$J$11=1),'Реестр рисков'!$A$11&" ","")&IF(AND('Реестр рисков'!$I$12=5,'Реестр рисков'!$J$12=1),'Реестр рисков'!$A$12&" ","")&IF(AND('Реестр рисков'!$I$13=5,'Реестр рисков'!$J$13=1),'Реестр рисков'!$A$13&" ","")&IF(AND('Реестр рисков'!$I$14=5,'Реестр рисков'!$J$14=1),'Реестр рисков'!$A$14&" ","")&IF(AND('Реестр рисков'!$I$15=5,'Реестр рисков'!$J$15=1),'Реестр рисков'!$A$15&" ","")&IF(AND('Реестр рисков'!$I$16=5,'Реестр рисков'!$J$16=1),'Реестр рисков'!$A$16&" ","")&IF(AND('Реестр рисков'!$I$17=5,'Реестр рисков'!$J$17=1),'Реестр рисков'!$A$17&" ","")&IF(AND('Реестр рисков'!$I$18=5,'Реестр рисков'!$J$18=1),'Реестр рисков'!$A$18&" ","")&IF(AND('Реестр рисков'!$I$19=5,'Реестр рисков'!$J$19=1),'Реестр рисков'!$A$19&" ","")&IF(AND('Реестр рисков'!$I$20=5,'Реестр рисков'!$J$20=1),'Реестр рисков'!$A$20&" ","")&IF(AND('Реестр рисков'!$I$21=5,'Реестр рисков'!$J$21=1),'Реестр рисков'!$A$21&" ","")&IF(AND('Реестр рисков'!$I$22=5,'Реестр рисков'!$J$22=1),'Реестр рисков'!$A$22&" ","")&IF(AND('Реестр рисков'!$I$23=5,'Реестр рисков'!$J$23=1),'Реестр рисков'!$A$23&" ","")&IF(AND('Реестр рисков'!$I$24=5,'Реестр рисков'!$J$24=1),'Реестр рисков'!$A$24&" ","")&IF(AND('Реестр рисков'!$I$25=5,'Реестр рисков'!$J$25=1),'Реестр рисков'!$A$25&" ","")) | D5: =TRIM(IF(AND('Реестр рисков'!$I$9=5,'Реестр рисков'!$J$9=2),'Реестр рисков'!$A$9&" ","")&IF(AND('Реестр рисков'!$I$10=5,'Реестр рисков'!$J$10=2),'Реестр рисков'!$A$10&" ","")&IF(AND('Реестр рисков'!$I$11=5,'Реестр рисков'!$J$11=2),'Реестр рисков'!$A$11&" ","")&IF(AND('Реестр рисков'!$I$12=5,'Реестр рисков'!$J$12=2),'Реестр рисков'!$A$12&" ","")&IF(AND('Реестр рисков'!$I$13=5,'Реестр рисков'!$J$13=2),'Реестр рисков'!$A$13&" ","")&IF(AND('Реестр рисков'!$I$14=5,'Реестр рисков'!$J$14=2),'Реестр рисков'!$A$14&" ","")&IF(AND('Реестр рисков'!$I$15=5,'Реестр рисков'!$J$15=2),'Реестр рисков'!$A$15&" ","")&IF(AND('Реестр рисков'!$I$16=5,'Реестр рисков'!$J$16=2),'Реестр рисков'!$A$16&" ","")&IF(AND('Реестр рисков'!$I$17=5,'Реестр рисков'!$J$17=2),'Реестр рисков'!$A$17&" ","")&IF(AND('Реестр рисков'!$I$18=5,'Реестр рисков'!$J$18=2),'Реестр рисков'!$A$18&" ","")&IF(AND('Реестр рисков'!$I$19=5,'Реестр рисков'!$J$19=2),'Реестр рисков'!$A$19&" ","")&IF(AND('Реестр рисков'!$I$20=5,'Реестр рисков'!$J$20=2),'Реестр рисков'!$A$20&" ","")&IF(AND('Реестр рисков'!$I$21=5,'Реестр рисков'!$J$21=2),'Реестр рисков'!$A$21&" ","")&IF(AND('Реестр рисков'!$I$22=5,'Реестр рисков'!$J$22=2),'Реестр рисков'!$A$22&" ","")&IF(AND('Реестр рисков'!$I$23=5,'Реестр рисков'!$J$23=2),'Реестр рисков'!$A$23&" ","")&IF(AND('Реестр рисков'!$I$24=5,'Реестр рисков'!$J$24=2),'Реестр рисков'!$A$24&" ","")&IF(AND('Реестр рисков'!$I$25=5,'Реестр рисков'!$J$25=2),'Реестр рисков'!$A$25&" ","")) | E5: =TRIM(IF(AND('Реестр рисков'!$I$9=5,'Реестр рисков'!$J$9=3),'Реестр рисков'!$A$9&" ","")&IF(AND('Реестр рисков'!$I$10=5,'Реестр рисков'!$J$10=3),'Реестр рисков'!$A$10&" ","")&IF(AND('Реестр рисков'!$I$11=5,'Реестр рисков'!$J$11=3),'Реестр рисков'!$A$11&" ","")&IF(AND('Реестр рисков'!$I$12=5,'Реестр рисков'!$J$12=3),'Реестр рисков'!$A$12&" ","")&IF(AND('Реестр рисков'!$I$13=5,'Реестр рисков'!$J$13=3),'Реестр рисков'!$A$13&" ","")&IF(AND('Реестр рисков'!$I$14=5,'Реестр рисков'!$J$14=3),'Реестр рисков'!$A$14&" ","")&IF(AND('Реестр рисков'!$I$15=5,'Реестр рисков'!$J$15=3),'Реестр рисков'!$A$15&" ","")&IF(AND('Реестр рисков'!$I$16=5,'Реестр рисков'!$J$16=3),'Реестр рисков'!$A$16&" ","")&IF(AND('Реестр рисков'!$I$17=5,'Реестр рисков'!$J$17=3),'Реестр рисков'!$A$17&" ","")&IF(AND('Реестр рисков'!$I$18=5,'Реестр рисков'!$J$18=3),'Реестр рисков'!$A$18&" ","")&IF(AND('Реестр рисков'!$I$19=5,'Реестр рисков'!$J$19=3),'Реестр рисков'!$A$19&" ","")&IF(AND('Реестр рисков'!$I$20=5,'Реестр рисков'!$J$20=3),'Реестр рисков'!$A$20&" ","")&IF(AND('Реестр рисков'!$I$21=5,'Реестр рисков'!$J$21=3),'Реестр рисков'!$A$21&" ","")&IF(AND('Реестр рисков'!$I$22=5,'Реестр рисков'!$J$22=3),'Реестр рисков'!$A$22&" ","")&IF(AND('Реестр рисков'!$I$23=5,'Реестр рисков'!$J$23=3),'Реестр рисков'!$A$23&" ","")&IF(AND('Реестр рисков'!$I$24=5,'Реестр рисков'!$J$24=3),'Реестр рисков'!$A$24&" ","")&IF(AND('Реестр рисков'!$I$25=5,'Реестр рисков'!$J$25=3),'Реестр рисков'!$A$25&" ","")) | F5: =TRIM(IF(AND('Реестр рисков'!$I$9=5,'Реестр рисков'!$J$9=4),'Реестр рисков'!$A$9&" ","")&IF(AND('Реестр рисков'!$I$10=5,'Реестр рисков'!$J$10=4),'Реестр рисков'!$A$10&" ","")&IF(AND('Реестр рисков'!$I$11=5,'Реестр рисков'!$J$11=4),'Реестр рисков'!$A$11&" ","")&IF(AND('Реестр рисков'!$I$12=5,'Реестр рисков'!$J$12=4),'Реестр рисков'!$A$12&" ","")&IF(AND('Реестр рисков'!$I$13=5,'Реестр рисков'!$J$13=4),'Реестр рисков'!$A$13&" ","")&IF(AND('Реестр рисков'!$I$14=5,'Реестр рисков'!$J$14=4),'Реестр рисков'!$A$14&" ","")&IF(AND('Реестр рисков'!$I$15=5,'Реестр рисков'!$J$15=4),'Реестр рисков'!$A$15&" ","")&IF(AND('Реестр рисков'!$I$16=5,'Реестр рисков'!$J$16=4),'Реестр рисков'!$A$16&" ","")&IF(AND('Реестр рисков'!$I$17=5,'Реестр рисков'!$J$17=4),'Реестр рисков'!$A$17&" ","")&IF(AND('Реестр рисков'!$I$18=5,'Реестр рисков'!$J$18=4),'Реестр рисков'!$A$18&" ","")&IF(AND('Реестр рисков'!$I$19=5,'Реестр рисков'!$J$19=4),'Реестр рисков'!$A$19&" ","")&IF(AND('Реестр рисков'!$I$20=5,'Реестр рисков'!$J$20=4),'Реестр рисков'!$A$20&" ","")&IF(AND('Реестр рисков'!$I$21=5,'Реестр рисков'!$J$21=4),'Реестр рисков'!$A$21&" ","")&IF(AND('Реестр рисков'!$I$22=5,'Реестр рисков'!$J$22=4),'Реестр рисков'!$A$22&" ","")&IF(AND('Реестр рисков'!$I$23=5,'Реестр рисков'!$J$23=4),'Реестр рисков'!$A$23&" ","")&IF(AND('Реестр рисков'!$I$24=5,'Реестр рисков'!$J$24=4),'Реестр рисков'!$A$24&" ","")&IF(AND('Реестр рисков'!$I$25=5,'Реестр рисков'!$J$25=4),'Реестр рисков'!$A$25&" ","")) | G5: =TRIM(IF(AND('Реестр рисков'!$I$9=5,'Реестр рисков'!$J$9=5),'Реестр рисков'!$A$9&" ","")&IF(AND('Реестр рисков'!$I$10=5,'Реестр рисков'!$J$10=5),'Реестр рисков'!$A$10&" ","")&IF(AND('Реестр рисков'!$I$11=5,'Реестр рисков'!$J$11=5),'Реестр рисков'!$A$11&" ","")&IF(AND('Реестр рисков'!$I$12=5,'Реестр рисков'!$J$12=5),'Реестр рисков'!$A$12&" ","")&IF(AND('Реестр рисков'!$I$13=5,'Реестр рисков'!$J$13=5),'Реестр рисков'!$A$13&" ","")&IF(AND('Реестр рисков'!$I$14=5,'Реестр рисков'!$J$14=5),'Реестр рисков'!$A$14&" ","")&IF(AND('Реестр рисков'!$I$15=5,'Реестр рисков'!$J$15=5),'Реестр рисков'!$A$15&" ","")&IF(AND('Реестр рисков'!$I$16=5,'Реестр рисков'!$J$16=5),'Реестр рисков'!$A$16&" ","")&IF(AND('Реестр рисков'!$I$17=5,'Реестр рисков'!$J$17=5),'Реестр рисков'!$A$17&" ","")&IF(AND('Реестр рисков'!$I$18=5,'Реестр рисков'!$J$18=5),'Реестр рисков'!$A$18&" ","")&IF(AND('Реестр рисков'!$I$19=5,'Реестр рисков'!$J$19=5),'Реестр рисков'!$A$19&" ","")&IF(AND('Реестр рисков'!$I$20=5,'Реестр рисков'!$J$20=5),'Реестр рисков'!$A$20&" ","")&IF(AND('Реестр рисков'!$I$21=5,'Реестр рисков'!$J$21=5),'Реестр рисков'!$A$21&" ","")&IF(AND('Реестр рисков'!$I$22=5,'Реестр рисков'!$J$22=5),'Реестр рисков'!$A$22&" ","")&IF(AND('Реестр рисков'!$I$23=5,'Реестр рисков'!$J$23=5),'Реестр рисков'!$A$23&" ","")&IF(AND('Реестр рисков'!$I$24=5,'Реестр рисков'!$J$24=5),'Реестр рисков'!$A$24&" ","")&IF(AND('Реестр рисков'!$I$25=5,'Реестр рисков'!$J$25=5),'Реестр рисков'!$A$25&" ","")) | I5: Риск | J5: Балл | K5: Приоритет | L5: Владелец
A6: 4 | B6: высокая | C6: =TRIM(IF(AND('Реестр рисков'!$I$9=4,'Реестр рисков'!$J$9=1),'Реестр рисков'!$A$9&" ","")&IF(AND('Реестр рисков'!$I$10=4,'Реестр рисков'!$J$10=1),'Реестр рисков'!$A$10&" ","")&IF(AND('Реестр рисков'!$I$11=4,'Реестр рисков'!$J$11=1),'Реестр рисков'!$A$11&" ","")&IF(AND('Реестр рисков'!$I$12=4,'Реестр рисков'!$J$12=1),'Реестр рисков'!$A$12&" ","")&IF(AND('Реестр рисков'!$I$13=4,'Реестр рисков'!$J$13=1),'Реестр рисков'!$A$13&" ","")&IF(AND('Реестр рисков'!$I$14=4,'Реестр рисков'!$J$14=1),'Реестр рисков'!$A$14&" ","")&IF(AND('Реестр рисков'!$I$15=4,'Реестр рисков'!$J$15=1),'Реестр рисков'!$A$15&" ","")&IF(AND('Реестр рисков'!$I$16=4,'Реестр рисков'!$J$16=1),'Реестр рисков'!$A$16&" ","")&IF(AND('Реестр рисков'!$I$17=4,'Реестр рисков'!$J$17=1),'Реестр рисков'!$A$17&" ","")&IF(AND('Реестр рисков'!$I$18=4,'Реестр рисков'!$J$18=1),'Реестр рисков'!$A$18&" ","")&IF(AND('Реестр рисков'!$I$19=4,'Реестр рисков'!$J$19=1),'Реестр рисков'!$A$19&" ","")&IF(AND('Реестр рисков'!$I$20=4,'Реестр рисков'!$J$20=1),'Реестр рисков'!$A$20&" ","")&IF(AND('Реестр рисков'!$I$21=4,'Реестр рисков'!$J$21=1),'Реестр рисков'!$A$21&" ","")&IF(AND('Реестр рисков'!$I$22=4,'Реестр рисков'!$J$22=1),'Реестр рисков'!$A$22&" ","")&IF(AND('Реестр рисков'!$I$23=4,'Реестр рисков'!$J$23=1),'Реестр рисков'!$A$23&" ","")&IF(AND('Реестр рисков'!$I$24=4,'Реестр рисков'!$J$24=1),'Реестр рисков'!$A$24&" ","")&IF(AND('Реестр рисков'!$I$25=4,'Реестр рисков'!$J$25=1),'Реестр рисков'!$A$25&" ","")) | D6: =TRIM(IF(AND('Реестр рисков'!$I$9=4,'Реестр рисков'!$J$9=2),'Реестр рисков'!$A$9&" ","")&IF(AND('Реестр рисков'!$I$10=4,'Реестр рисков'!$J$10=2),'Реестр рисков'!$A$10&" ","")&IF(AND('Реестр рисков'!$I$11=4,'Реестр рисков'!$J$11=2),'Реестр рисков'!$A$11&" ","")&IF(AND('Реестр рисков'!$I$12=4,'Реестр рисков'!$J$12=2),'Реестр рисков'!$A$12&" ","")&IF(AND('Реестр рисков'!$I$13=4,'Реестр рисков'!$J$13=2),'Реестр рисков'!$A$13&" ","")&IF(AND('Реестр рисков'!$I$14=4,'Реестр рисков'!$J$14=2),'Реестр рисков'!$A$14&" ","")&IF(AND('Реестр рисков'!$I$15=4,'Реестр рисков'!$J$15=2),'Реестр рисков'!$A$15&" ","")&IF(AND('Реестр рисков'!$I$16=4,'Реестр рисков'!$J$16=2),'Реестр рисков'!$A$16&" ","")&IF(AND('Реестр рисков'!$I$17=4,'Реестр рисков'!$J$17=2),'Реестр рисков'!$A$17&" ","")&IF(AND('Реестр рисков'!$I$18=4,'Реестр рисков'!$J$18=2),'Реестр рисков'!$A$18&" ","")&IF(AND('Реестр рисков'!$I$19=4,'Реестр рисков'!$J$19=2),'Реестр рисков'!$A$19&" ","")&IF(AND('Реестр рисков'!$I$20=4,'Реестр рисков'!$J$20=2),'Реестр рисков'!$A$20&" ","")&IF(AND('Реестр рисков'!$I$21=4,'Реестр рисков'!$J$21=2),'Реестр рисков'!$A$21&" ","")&IF(AND('Реестр рисков'!$I$22=4,'Реестр рисков'!$J$22=2),'Реестр рисков'!$A$22&" ","")&IF(AND('Реестр рисков'!$I$23=4,'Реестр рисков'!$J$23=2),'Реестр рисков'!$A$23&" ","")&IF(AND('Реестр рисков'!$I$24=4,'Реестр рисков'!$J$24=2),'Реестр рисков'!$A$24&" ","")&IF(AND('Реестр рисков'!$I$25=4,'Реестр рисков'!$J$25=2),'Реестр рисков'!$A$25&" ","")) | E6: =TRIM(IF(AND('Реестр рисков'!$I$9=4,'Реестр рисков'!$J$9=3),'Реестр рисков'!$A$9&" ","")&IF(AND('Реестр рисков'!$I$10=4,'Реестр рисков'!$J$10=3),'Реестр рисков'!$A$10&" ","")&IF(AND('Реестр рисков'!$I$11=4,'Реестр рисков'!$J$11=3),'Реестр рисков'!$A$11&" ","")&IF(AND('Реестр рисков'!$I$12=4,'Реестр рисков'!$J$12=3),'Реестр рисков'!$A$12&" ","")&IF(AND('Реестр рисков'!$I$13=4,'Реестр рисков'!$J$13=3),'Реестр рисков'!$A$13&" ","")&IF(AND('Реестр рисков'!$I$14=4,'Реестр рисков'!$J$14=3),'Реестр рисков'!$A$14&" ","")&IF(AND('Реестр рисков'!$I$15=4,'Реестр рисков'!$J$15=3),'Реестр рисков'!$A$15&" ","")&IF(AND('Реестр рисков'!$I$16=4,'Реестр рисков'!$J$16=3),'Реестр рисков'!$A$16&" ","")&IF(AND('Реестр рисков'!$I$17=4,'Реестр рисков'!$J$17=3),'Реестр рисков'!$A$17&" ","")&IF(AND('Реестр рисков'!$I$18=4,'Реестр рисков'!$J$18=3),'Реестр рисков'!$A$18&" ","")&IF(AND('Реестр рисков'!$I$19=4,'Реестр рисков'!$J$19=3),'Реестр рисков'!$A$19&" ","")&IF(AND('Реестр рисков'!$I$20=4,'Реестр рисков'!$J$20=3),'Реестр рисков'!$A$20&" ","")&IF(AND('Реестр рисков'!$I$21=4,'Реестр рисков'!$J$21=3),'Реестр рисков'!$A$21&" ","")&IF(AND('Реестр рисков'!$I$22=4,'Реестр рисков'!$J$22=3),'Реестр рисков'!$A$22&" ","")&IF(AND('Реестр рисков'!$I$23=4,'Реестр рисков'!$J$23=3),'Реестр рисков'!$A$23&" ","")&IF(AND('Реестр рисков'!$I$24=4,'Реестр рисков'!$J$24=3),'Реестр рисков'!$A$24&" ","")&IF(AND('Реестр рисков'!$I$25=4,'Реестр рисков'!$J$25=3),'Реестр рисков'!$A$25&" ","")) -> Р1 | F6: =TRIM(IF(AND('Реестр рисков'!$I$9=4,'Реестр рисков'!$J$9=4),'Реестр рисков'!$A$9&" ","")&IF(AND('Реестр рисков'!$I$10=4,'Реестр рисков'!$J$10=4),'Реестр рисков'!$A$10&" ","")&IF(AND('Реестр рисков'!$I$11=4,'Реестр рисков'!$J$11=4),'Реестр рисков'!$A$11&" ","")&IF(AND('Реестр рисков'!$I$12=4,'Реестр рисков'!$J$12=4),'Реестр рисков'!$A$12&" ","")&IF(AND('Реестр рисков'!$I$13=4,'Реестр рисков'!$J$13=4),'Реестр рисков'!$A$13&" ","")&IF(AND('Реестр рисков'!$I$14=4,'Реестр рисков'!$J$14=4),'Реестр рисков'!$A$14&" ","")&IF(AND('Реестр рисков'!$I$15=4,'Реестр рисков'!$J$15=4),'Реестр рисков'!$A$15&" ","")&IF(AND('Реестр рисков'!$I$16=4,'Реестр рисков'!$J$16=4),'Реестр рисков'!$A$16&" ","")&IF(AND('Реестр рисков'!$I$17=4,'Реестр рисков'!$J$17=4),'Реестр рисков'!$A$17&" ","")&IF(AND('Реестр рисков'!$I$18=4,'Реестр рисков'!$J$18=4),'Реестр рисков'!$A$18&" ","")&IF(AND('Реестр рисков'!$I$19=4,'Реестр рисков'!$J$19=4),'Реестр рисков'!$A$19&" ","")&IF(AND('Реестр рисков'!$I$20=4,'Реестр рисков'!$J$20=4),'Реестр рисков'!$A$20&" ","")&IF(AND('Реестр рисков'!$I$21=4,'Реестр рисков'!$J$21=4),'Реестр рисков'!$A$21&" ","")&IF(AND('Реестр рисков'!$I$22=4,'Реестр рисков'!$J$22=4),'Реестр рисков'!$A$22&" ","")&IF(AND('Реестр рисков'!$I$23=4,'Реестр рисков'!$J$23=4),'Реестр рисков'!$A$23&" ","")&IF(AND('Реестр рисков'!$I$24=4,'Реестр рисков'!$J$24=4),'Реестр рисков'!$A$24&" ","")&IF(AND('Реестр рисков'!$I$25=4,'Реестр рисков'!$J$25=4),'Реестр рисков'!$A$25&" ","")) -> Р7 | G6: =TRIM(IF(AND('Реестр рисков'!$I$9=4,'Реестр рисков'!$J$9=5),'Реестр рисков'!$A$9&" ","")&IF(AND('Реестр рисков'!$I$10=4,'Реестр рисков'!$J$10=5),'Реестр рисков'!$A$10&" ","")&IF(AND('Реестр рисков'!$I$11=4,'Реестр рисков'!$J$11=5),'Реестр рисков'!$A$11&" ","")&IF(AND('Реестр рисков'!$I$12=4,'Реестр рисков'!$J$12=5),'Реестр рисков'!$A$12&" ","")&IF(AND('Реестр рисков'!$I$13=4,'Реестр рисков'!$J$13=5),'Реестр рисков'!$A$13&" ","")&IF(AND('Реестр рисков'!$I$14=4,'Реестр рисков'!$J$14=5),'Реестр рисков'!$A$14&" ","")&IF(AND('Реестр рисков'!$I$15=4,'Реестр рисков'!$J$15=5),'Реестр рисков'!$A$15&" ","")&IF(AND('Реестр рисков'!$I$16=4,'Реестр рисков'!$J$16=5),'Реестр рисков'!$A$16&" ","")&IF(AND('Реестр рисков'!$I$17=4,'Реестр рисков'!$J$17=5),'Реестр рисков'!$A$17&" ","")&IF(AND('Реестр рисков'!$I$18=4,'Реестр рисков'!$J$18=5),'Реестр рисков'!$A$18&" ","")&IF(AND('Реестр рисков'!$I$19=4,'Реестр рисков'!$J$19=5),'Реестр рисков'!$A$19&" ","")&IF(AND('Реестр рисков'!$I$20=4,'Реестр рисков'!$J$20=5),'Реестр рисков'!$A$20&" ","")&IF(AND('Реестр рисков'!$I$21=4,'Реестр рисков'!$J$21=5),'Реестр рисков'!$A$21&" ","")&IF(AND('Реестр рисков'!$I$22=4,'Реестр рисков'!$J$22=5),'Реестр рисков'!$A$22&" ","")&IF(AND('Реестр рисков'!$I$23=4,'Реестр рисков'!$J$23=5),'Реестр рисков'!$A$23&" ","")&IF(AND('Реестр рисков'!$I$24=4,'Реестр рисков'!$J$24=5),'Реестр рисков'!$A$24&" ","")&IF(AND('Реестр рисков'!$I$25=4,'Реестр рисков'!$J$25=5),'Реестр рисков'!$A$25&" ","")) | I6: =INDEX('Реестр рисков'!$A$9:$A$25,MATCH(1,'Реестр рисков'!$T$9:$T$25,0))&". "&INDEX('Реестр рисков'!$C$9:$C$25,MATCH(1,'Реестр рисков'!$T$9:$T$25,0)) -> Р7. Нехватка времени участников из-за учёбы | J6: =INDEX('Реестр рисков'!$K$9:$K$25,MATCH(1,'Реестр рисков'!$T$9:$T$25,0)) -> 16 | K6: =INDEX('Реестр рисков'!$L$9:$L$25,MATCH(1,'Реестр рисков'!$T$9:$T$25,0)) -> Высокий | L6: =INDEX('Реестр рисков'!$P$9:$P$25,MATCH(1,'Реестр рисков'!$T$9:$T$25,0)) -> Лопатин Д.И.
A7: 3 | B7: средняя | C7: =TRIM(IF(AND('Реестр рисков'!$I$9=3,'Реестр рисков'!$J$9=1),'Реестр рисков'!$A$9&" ","")&IF(AND('Реестр рисков'!$I$10=3,'Реестр рисков'!$J$10=1),'Реестр рисков'!$A$10&" ","")&IF(AND('Реестр рисков'!$I$11=3,'Реестр рисков'!$J$11=1),'Реестр рисков'!$A$11&" ","")&IF(AND('Реестр рисков'!$I$12=3,'Реестр рисков'!$J$12=1),'Реестр рисков'!$A$12&" ","")&IF(AND('Реестр рисков'!$I$13=3,'Реестр рисков'!$J$13=1),'Реестр рисков'!$A$13&" ","")&IF(AND('Реестр рисков'!$I$14=3,'Реестр рисков'!$J$14=1),'Реестр рисков'!$A$14&" ","")&IF(AND('Реестр рисков'!$I$15=3,'Реестр рисков'!$J$15=1),'Реестр рисков'!$A$15&" ","")&IF(AND('Реестр рисков'!$I$16=3,'Реестр рисков'!$J$16=1),'Реестр рисков'!$A$16&" ","")&IF(AND('Реестр рисков'!$I$17=3,'Реестр рисков'!$J$17=1),'Реестр рисков'!$A$17&" ","")&IF(AND('Реестр рисков'!$I$18=3,'Реестр рисков'!$J$18=1),'Реестр рисков'!$A$18&" ","")&IF(AND('Реестр рисков'!$I$19=3,'Реестр рисков'!$J$19=1),'Реестр рисков'!$A$19&" ","")&IF(AND('Реестр рисков'!$I$20=3,'Реестр рисков'!$J$20=1),'Реестр рисков'!$A$20&" ","")&IF(AND('Реестр рисков'!$I$21=3,'Реестр рисков'!$J$21=1),'Реестр рисков'!$A$21&" ","")&IF(AND('Реестр рисков'!$I$22=3,'Реестр рисков'!$J$22=1),'Реестр рисков'!$A$22&" ","")&IF(AND('Реестр рисков'!$I$23=3,'Реестр рисков'!$J$23=1),'Реестр рисков'!$A$23&" ","")&IF(AND('Реестр рисков'!$I$24=3,'Реестр рисков'!$J$24=1),'Реестр рисков'!$A$24&" ","")&IF(AND('Реестр рисков'!$I$25=3,'Реестр рисков'!$J$25=1),'Реестр рисков'!$A$25&" ","")) | D7: =TRIM(IF(AND('Реестр рисков'!$I$9=3,'Реестр рисков'!$J$9=2),'Реестр рисков'!$A$9&" ","")&IF(AND('Реестр рисков'!$I$10=3,'Реестр рисков'!$J$10=2),'Реестр рисков'!$A$10&" ","")&IF(AND('Реестр рисков'!$I$11=3,'Реестр рисков'!$J$11=2),'Реестр рисков'!$A$11&" ","")&IF(AND('Реестр рисков'!$I$12=3,'Реестр рисков'!$J$12=2),'Реестр рисков'!$A$12&" ","")&IF(AND('Реестр рисков'!$I$13=3,'Реестр рисков'!$J$13=2),'Реестр рисков'!$A$13&" ","")&IF(AND('Реестр рисков'!$I$14=3,'Реестр рисков'!$J$14=2),'Реестр рисков'!$A$14&" ","")&IF(AND('Реестр рисков'!$I$15=3,'Реестр рисков'!$J$15=2),'Реестр рисков'!$A$15&" ","")&IF(AND('Реестр рисков'!$I$16=3,'Реестр рисков'!$J$16=2),'Реестр рисков'!$A$16&" ","")&IF(AND('Реестр рисков'!$I$17=3,'Реестр рисков'!$J$17=2),'Реестр рисков'!$A$17&" ","")&IF(AND('Реестр рисков'!$I$18=3,'Реестр рисков'!$J$18=2),'Реестр рисков'!$A$18&" ","")&IF(AND('Реестр рисков'!$I$19=3,'Реестр рисков'!$J$19=2),'Реестр рисков'!$A$19&" ","")&IF(AND('Реестр рисков'!$I$20=3,'Реестр рисков'!$J$20=2),'Реестр рисков'!$A$20&" ","")&IF(AND('Реестр рисков'!$I$21=3,'Реестр рисков'!$J$21=2),'Реестр рисков'!$A$21&" ","")&IF(AND('Реестр рисков'!$I$22=3,'Реестр рисков'!$J$22=2),'Реестр рисков'!$A$22&" ","")&IF(AND('Реестр рисков'!$I$23=3,'Реестр рисков'!$J$23=2),'Реестр рисков'!$A$23&" ","")&IF(AND('Реестр рисков'!$I$24=3,'Реестр рисков'!$J$24=2),'Реестр рисков'!$A$24&" ","")&IF(AND('Реестр рисков'!$I$25=3,'Реестр рисков'!$J$25=2),'Реестр рисков'!$A$25&" ","")) | E7: =TRIM(IF(AND('Реестр рисков'!$I$9=3,'Реестр рисков'!$J$9=3),'Реестр рисков'!$A$9&" ","")&IF(AND('Реестр рисков'!$I$10=3,'Реестр рисков'!$J$10=3),'Реестр рисков'!$A$10&" ","")&IF(AND('Реестр рисков'!$I$11=3,'Реестр рисков'!$J$11=3),'Реестр рисков'!$A$11&" ","")&IF(AND('Реестр рисков'!$I$12=3,'Реестр рисков'!$J$12=3),'Реестр рисков'!$A$12&" ","")&IF(AND('Реестр рисков'!$I$13=3,'Реестр рисков'!$J$13=3),'Реестр рисков'!$A$13&" ","")&IF(AND('Реестр рисков'!$I$14=3,'Реестр рисков'!$J$14=3),'Реестр рисков'!$A$14&" ","")&IF(AND('Реестр рисков'!$I$15=3,'Реестр рисков'!$J$15=3),'Реестр рисков'!$A$15&" ","")&IF(AND('Реестр рисков'!$I$16=3,'Реестр рисков'!$J$16=3),'Реестр рисков'!$A$16&" ","")&IF(AND('Реестр рисков'!$I$17=3,'Реестр рисков'!$J$17=3),'Реестр рисков'!$A$17&" ","")&IF(AND('Реестр рисков'!$I$18=3,'Реестр рисков'!$J$18=3),'Реестр рисков'!$A$18&" ","")&IF(AND('Реестр рисков'!$I$19=3,'Реестр рисков'!$J$19=3),'Реестр рисков'!$A$19&" ","")&IF(AND('Реестр рисков'!$I$20=3,'Реестр рисков'!$J$20=3),'Реестр рисков'!$A$20&" ","")&IF(AND('Реестр рисков'!$I$21=3,'Реестр рисков'!$J$21=3),'Реестр рисков'!$A$21&" ","")&IF(AND('Реестр рисков'!$I$22=3,'Реестр рисков'!$J$22=3),'Реестр рисков'!$A$22&" ","")&IF(AND('Реестр рисков'!$I$23=3,'Реестр рисков'!$J$23=3),'Реестр рисков'!$A$23&" ","")&IF(AND('Реестр рисков'!$I$24=3,'Реестр рисков'!$J$24=3),'Реестр рисков'!$A$24&" ","")&IF(AND('Реестр рисков'!$I$25=3,'Реестр рисков'!$J$25=3),'Реестр рисков'!$A$25&" ","")) -> Р2 Р6 Р13 | F7: =TRIM(IF(AND('Реестр рисков'!$I$9=3,'Реестр рисков'!$J$9=4),'Реестр рисков'!$A$9&" ","")&IF(AND('Реестр рисков'!$I$10=3,'Реестр рисков'!$J$10=4),'Реестр рисков'!$A$10&" ","")&IF(AND('Реестр рисков'!$I$11=3,'Реестр рисков'!$J$11=4),'Реестр рисков'!$A$11&" ","")&IF(AND('Реестр рисков'!$I$12=3,'Реестр рисков'!$J$12=4),'Реестр рисков'!$A$12&" ","")&IF(AND('Реестр рисков'!$I$13=3,'Реестр рисков'!$J$13=4),'Реестр рисков'!$A$13&" ","")&IF(AND('Реестр рисков'!$I$14=3,'Реестр рисков'!$J$14=4),'Реестр рисков'!$A$14&" ","")&IF(AND('Реестр рисков'!$I$15=3,'Реестр рисков'!$J$15=4),'Реестр рисков'!$A$15&" ","")&IF(AND('Реестр рисков'!$I$16=3,'Реестр рисков'!$J$16=4),'Реестр рисков'!$A$16&" ","")&IF(AND('Реестр рисков'!$I$17=3,'Реестр рисков'!$J$17=4),'Реестр рисков'!$A$17&" ","")&IF(AND('Реестр рисков'!$I$18=3,'Реестр рисков'!$J$18=4),'Реестр рисков'!$A$18&" ","")&IF(AND('Реестр рисков'!$I$19=3,'Реестр рисков'!$J$19=4),'Реестр рисков'!$A$19&" ","")&IF(AND('Реестр рисков'!$I$20=3,'Реестр рисков'!$J$20=4),'Реестр рисков'!$A$20&" ","")&IF(AND('Реестр рисков'!$I$21=3,'Реестр рисков'!$J$21=4),'Реестр рисков'!$A$21&" ","")&IF(AND('Реестр рисков'!$I$22=3,'Реестр рисков'!$J$22=4),'Реестр рисков'!$A$22&" ","")&IF(AND('Реестр рисков'!$I$23=3,'Реестр рисков'!$J$23=4),'Реестр рисков'!$A$23&" ","")&IF(AND('Реестр рисков'!$I$24=3,'Реестр рисков'!$J$24=4),'Реестр рисков'!$A$24&" ","")&IF(AND('Реестр рисков'!$I$25=3,'Реестр рисков'!$J$25=4),'Реестр рисков'!$A$25&" ","")) -> Р8 Р10 Р12 | G7: =TRIM(IF(AND('Реестр рисков'!$I$9=3,'Реестр рисков'!$J$9=5),'Реестр рисков'!$A$9&" ","")&IF(AND('Реестр рисков'!$I$10=3,'Реестр рисков'!$J$10=5),'Реестр рисков'!$A$10&" ","")&IF(AND('Реестр рисков'!$I$11=3,'Реестр рисков'!$J$11=5),'Реестр рисков'!$A$11&" ","")&IF(AND('Реестр рисков'!$I$12=3,'Реестр рисков'!$J$12=5),'Реестр рисков'!$A$12&" ","")&IF(AND('Реестр рисков'!$I$13=3,'Реестр рисков'!$J$13=5),'Реестр рисков'!$A$13&" ","")&IF(AND('Реестр рисков'!$I$14=3,'Реестр рисков'!$J$14=5),'Реестр рисков'!$A$14&" ","")&IF(AND('Реестр рисков'!$I$15=3,'Реестр рисков'!$J$15=5),'Реестр рисков'!$A$15&" ","")&IF(AND('Реестр рисков'!$I$16=3,'Реестр рисков'!$J$16=5),'Реестр рисков'!$A$16&" ","")&IF(AND('Реестр рисков'!$I$17=3,'Реестр рисков'!$J$17=5),'Реестр рисков'!$A$17&" ","")&IF(AND('Реестр рисков'!$I$18=3,'Реестр рисков'!$J$18=5),'Реестр рисков'!$A$18&" ","")&IF(AND('Реестр рисков'!$I$19=3,'Реестр рисков'!$J$19=5),'Реестр рисков'!$A$19&" ","")&IF(AND('Реестр рисков'!$I$20=3,'Реестр рисков'!$J$20=5),'Реестр рисков'!$A$20&" ","")&IF(AND('Реестр рисков'!$I$21=3,'Реестр рисков'!$J$21=5),'Реестр рисков'!$A$21&" ","")&IF(AND('Реестр рисков'!$I$22=3,'Реестр рисков'!$J$22=5),'Реестр рисков'!$A$22&" ","")&IF(AND('Реестр рисков'!$I$23=3,'Реестр рисков'!$J$23=5),'Реестр рисков'!$A$23&" ","")&IF(AND('Реестр рисков'!$I$24=3,'Реестр рисков'!$J$24=5),'Реестр рисков'!$A$24&" ","")&IF(AND('Реестр рисков'!$I$25=3,'Реестр рисков'!$J$25=5),'Реестр рисков'!$A$25&" ","")) -> Р11 | I7: =INDEX('Реестр рисков'!$A$9:$A$25,MATCH(2,'Реестр рисков'!$T$9:$T$25,0))&". "&INDEX('Реестр рисков'!$C$9:$C$25,MATCH(2,'Реестр рисков'!$T$9:$T$25,0)) -> Р11. Запрос на изменение № 1 не согласован | J7: =INDEX('Реестр рисков'!$K$9:$K$25,MATCH(2,'Реестр рисков'!$T$9:$T$25,0)) -> 15 | K7: =INDEX('Реестр рисков'!$L$9:$L$25,MATCH(2,'Реестр рисков'!$T$9:$T$25,0)) -> Высокий | L7: =INDEX('Реестр рисков'!$P$9:$P$25,MATCH(2,'Реестр рисков'!$T$9:$T$25,0)) -> Лопатин Д.И.
A8: 2 | B8: низкая | C8: =TRIM(IF(AND('Реестр рисков'!$I$9=2,'Реестр рисков'!$J$9=1),'Реестр рисков'!$A$9&" ","")&IF(AND('Реестр рисков'!$I$10=2,'Реестр рисков'!$J$10=1),'Реестр рисков'!$A$10&" ","")&IF(AND('Реестр рисков'!$I$11=2,'Реестр рисков'!$J$11=1),'Реестр рисков'!$A$11&" ","")&IF(AND('Реестр рисков'!$I$12=2,'Реестр рисков'!$J$12=1),'Реестр рисков'!$A$12&" ","")&IF(AND('Реестр рисков'!$I$13=2,'Реестр рисков'!$J$13=1),'Реестр рисков'!$A$13&" ","")&IF(AND('Реестр рисков'!$I$14=2,'Реестр рисков'!$J$14=1),'Реестр рисков'!$A$14&" ","")&IF(AND('Реестр рисков'!$I$15=2,'Реестр рисков'!$J$15=1),'Реестр рисков'!$A$15&" ","")&IF(AND('Реестр рисков'!$I$16=2,'Реестр рисков'!$J$16=1),'Реестр рисков'!$A$16&" ","")&IF(AND('Реестр рисков'!$I$17=2,'Реестр рисков'!$J$17=1),'Реестр рисков'!$A$17&" ","")&IF(AND('Реестр рисков'!$I$18=2,'Реестр рисков'!$J$18=1),'Реестр рисков'!$A$18&" ","")&IF(AND('Реестр рисков'!$I$19=2,'Реестр рисков'!$J$19=1),'Реестр рисков'!$A$19&" ","")&IF(AND('Реестр рисков'!$I$20=2,'Реестр рисков'!$J$20=1),'Реестр рисков'!$A$20&" ","")&IF(AND('Реестр рисков'!$I$21=2,'Реестр рисков'!$J$21=1),'Реестр рисков'!$A$21&" ","")&IF(AND('Реестр рисков'!$I$22=2,'Реестр рисков'!$J$22=1),'Реестр рисков'!$A$22&" ","")&IF(AND('Реестр рисков'!$I$23=2,'Реестр рисков'!$J$23=1),'Реестр рисков'!$A$23&" ","")&IF(AND('Реестр рисков'!$I$24=2,'Реестр рисков'!$J$24=1),'Реестр рисков'!$A$24&" ","")&IF(AND('Реестр рисков'!$I$25=2,'Реестр рисков'!$J$25=1),'Реестр рисков'!$A$25&" ","")) | D8: =TRIM(IF(AND('Реестр рисков'!$I$9=2,'Реестр рисков'!$J$9=2),'Реестр рисков'!$A$9&" ","")&IF(AND('Реестр рисков'!$I$10=2,'Реестр рисков'!$J$10=2),'Реестр рисков'!$A$10&" ","")&IF(AND('Реестр рисков'!$I$11=2,'Реестр рисков'!$J$11=2),'Реестр рисков'!$A$11&" ","")&IF(AND('Реестр рисков'!$I$12=2,'Реестр рисков'!$J$12=2),'Реестр рисков'!$A$12&" ","")&IF(AND('Реестр рисков'!$I$13=2,'Реестр рисков'!$J$13=2),'Реестр рисков'!$A$13&" ","")&IF(AND('Реестр рисков'!$I$14=2,'Реестр рисков'!$J$14=2),'Реестр рисков'!$A$14&" ","")&IF(AND('Реестр рисков'!$I$15=2,'Реестр рисков'!$J$15=2),'Реестр рисков'!$A$15&" ","")&IF(AND('Реестр рисков'!$I$16=2,'Реестр рисков'!$J$16=2),'Реестр рисков'!$A$16&" ","")&IF(AND('Реестр рисков'!$I$17=2,'Реестр рисков'!$J$17=2),'Реестр рисков'!$A$17&" ","")&IF(AND('Реестр рисков'!$I$18=2,'Реестр рисков'!$J$18=2),'Реестр рисков'!$A$18&" ","")&IF(AND('Реестр рисков'!$I$19=2,'Реестр рисков'!$J$19=2),'Реестр рисков'!$A$19&" ","")&IF(AND('Реестр рисков'!$I$20=2,'Реестр рисков'!$J$20=2),'Реестр рисков'!$A$20&" ","")&IF(AND('Реестр рисков'!$I$21=2,'Реестр рисков'!$J$21=2),'Реестр рисков'!$A$21&" ","")&IF(AND('Реестр рисков'!$I$22=2,'Реестр рисков'!$J$22=2),'Реестр рисков'!$A$22&" ","")&IF(AND('Реестр рисков'!$I$23=2,'Реестр рисков'!$J$23=2),'Реестр рисков'!$A$23&" ","")&IF(AND('Реестр рисков'!$I$24=2,'Реестр рисков'!$J$24=2),'Реестр рисков'!$A$24&" ","")&IF(AND('Реестр рисков'!$I$25=2,'Реестр рисков'!$J$25=2),'Реестр рисков'!$A$25&" ","")) -> Р4 Р9 Р17 | E8: =TRIM(IF(AND('Реестр рисков'!$I$9=2,'Реестр рисков'!$J$9=3),'Реестр рисков'!$A$9&" ","")&IF(AND('Реестр рисков'!$I$10=2,'Реестр рисков'!$J$10=3),'Реестр рисков'!$A$10&" ","")&IF(AND('Реестр рисков'!$I$11=2,'Реестр рисков'!$J$11=3),'Реестр рисков'!$A$11&" ","")&IF(AND('Реестр рисков'!$I$12=2,'Реестр рисков'!$J$12=3),'Реестр рисков'!$A$12&" ","")&IF(AND('Реестр рисков'!$I$13=2,'Реестр рисков'!$J$13=3),'Реестр рисков'!$A$13&" ","")&IF(AND('Реестр рисков'!$I$14=2,'Реестр рисков'!$J$14=3),'Реестр рисков'!$A$14&" ","")&IF(AND('Реестр рисков'!$I$15=2,'Реестр рисков'!$J$15=3),'Реестр рисков'!$A$15&" ","")&IF(AND('Реестр рисков'!$I$16=2,'Реестр рисков'!$J$16=3),'Реестр рисков'!$A$16&" ","")&IF(AND('Реестр рисков'!$I$17=2,'Реестр рисков'!$J$17=3),'Реестр рисков'!$A$17&" ","")&IF(AND('Реестр рисков'!$I$18=2,'Реестр рисков'!$J$18=3),'Реестр рисков'!$A$18&" ","")&IF(AND('Реестр рисков'!$I$19=2,'Реестр рисков'!$J$19=3),'Реестр рисков'!$A$19&" ","")&IF(AND('Реестр рисков'!$I$20=2,'Реестр рисков'!$J$20=3),'Реестр рисков'!$A$20&" ","")&IF(AND('Реестр рисков'!$I$21=2,'Реестр рисков'!$J$21=3),'Реестр рисков'!$A$21&" ","")&IF(AND('Реестр рисков'!$I$22=2,'Реестр рисков'!$J$22=3),'Реестр рисков'!$A$22&" ","")&IF(AND('Реестр рисков'!$I$23=2,'Реестр рисков'!$J$23=3),'Реестр рисков'!$A$23&" ","")&IF(AND('Реестр рисков'!$I$24=2,'Реестр рисков'!$J$24=3),'Реестр рисков'!$A$24&" ","")&IF(AND('Реестр рисков'!$I$25=2,'Реестр рисков'!$J$25=3),'Реестр рисков'!$A$25&" ","")) -> Р15 Р16 | F8: =TRIM(IF(AND('Реестр рисков'!$I$9=2,'Реестр рисков'!$J$9=4),'Реестр рисков'!$A$9&" ","")&IF(AND('Реестр рисков'!$I$10=2,'Реестр рисков'!$J$10=4),'Реестр рисков'!$A$10&" ","")&IF(AND('Реестр рисков'!$I$11=2,'Реестр рисков'!$J$11=4),'Реестр рисков'!$A$11&" ","")&IF(AND('Реестр рисков'!$I$12=2,'Реестр рисков'!$J$12=4),'Реестр рисков'!$A$12&" ","")&IF(AND('Реестр рисков'!$I$13=2,'Реестр рисков'!$J$13=4),'Реестр рисков'!$A$13&" ","")&IF(AND('Реестр рисков'!$I$14=2,'Реестр рисков'!$J$14=4),'Реестр рисков'!$A$14&" ","")&IF(AND('Реестр рисков'!$I$15=2,'Реестр рисков'!$J$15=4),'Реестр рисков'!$A$15&" ","")&IF(AND('Реестр рисков'!$I$16=2,'Реестр рисков'!$J$16=4),'Реестр рисков'!$A$16&" ","")&IF(AND('Реестр рисков'!$I$17=2,'Реестр рисков'!$J$17=4),'Реестр рисков'!$A$17&" ","")&IF(AND('Реестр рисков'!$I$18=2,'Реестр рисков'!$J$18=4),'Реестр рисков'!$A$18&" ","")&IF(AND('Реестр рисков'!$I$19=2,'Реестр рисков'!$J$19=4),'Реестр рисков'!$A$19&" ","")&IF(AND('Реестр рисков'!$I$20=2,'Реестр рисков'!$J$20=4),'Реестр рисков'!$A$20&" ","")&IF(AND('Реестр рисков'!$I$21=2,'Реестр рисков'!$J$21=4),'Реестр рисков'!$A$21&" ","")&IF(AND('Реестр рисков'!$I$22=2,'Реестр рисков'!$J$22=4),'Реестр рисков'!$A$22&" ","")&IF(AND('Реестр рисков'!$I$23=2,'Реестр рисков'!$J$23=4),'Реестр рисков'!$A$23&" ","")&IF(AND('Реестр рисков'!$I$24=2,'Реестр рисков'!$J$24=4),'Реестр рисков'!$A$24&" ","")&IF(AND('Реестр рисков'!$I$25=2,'Реестр рисков'!$J$25=4),'Реестр рисков'!$A$25&" ","")) -> Р3 | G8: =TRIM(IF(AND('Реестр рисков'!$I$9=2,'Реестр рисков'!$J$9=5),'Реестр рисков'!$A$9&" ","")&IF(AND('Реестр рисков'!$I$10=2,'Реестр рисков'!$J$10=5),'Реестр рисков'!$A$10&" ","")&IF(AND('Реестр рисков'!$I$11=2,'Реестр рисков'!$J$11=5),'Реестр рисков'!$A$11&" ","")&IF(AND('Реестр рисков'!$I$12=2,'Реестр рисков'!$J$12=5),'Реестр рисков'!$A$12&" ","")&IF(AND('Реестр рисков'!$I$13=2,'Реестр рисков'!$J$13=5),'Реестр рисков'!$A$13&" ","")&IF(AND('Реестр рисков'!$I$14=2,'Реестр рисков'!$J$14=5),'Реестр рисков'!$A$14&" ","")&IF(AND('Реестр рисков'!$I$15=2,'Реестр рисков'!$J$15=5),'Реестр рисков'!$A$15&" ","")&IF(AND('Реестр рисков'!$I$16=2,'Реестр рисков'!$J$16=5),'Реестр рисков'!$A$16&" ","")&IF(AND('Реестр рисков'!$I$17=2,'Реестр рисков'!$J$17=5),'Реестр рисков'!$A$17&" ","")&IF(AND('Реестр рисков'!$I$18=2,'Реестр рисков'!$J$18=5),'Реестр рисков'!$A$18&" ","")&IF(AND('Реестр рисков'!$I$19=2,'Реестр рисков'!$J$19=5),'Реестр рисков'!$A$19&" ","")&IF(AND('Реестр рисков'!$I$20=2,'Реестр рисков'!$J$20=5),'Реестр рисков'!$A$20&" ","")&IF(AND('Реестр рисков'!$I$21=2,'Реестр рисков'!$J$21=5),'Реестр рисков'!$A$21&" ","")&IF(AND('Реестр рисков'!$I$22=2,'Реестр рисков'!$J$22=5),'Реестр рисков'!$A$22&" ","")&IF(AND('Реестр рисков'!$I$23=2,'Реестр рисков'!$J$23=5),'Реестр рисков'!$A$23&" ","")&IF(AND('Реестр рисков'!$I$24=2,'Реестр рисков'!$J$24=5),'Реестр рисков'!$A$24&" ","")&IF(AND('Реестр рисков'!$I$25=2,'Реестр рисков'!$J$25=5),'Реестр рисков'!$A$25&" ","")) -> Р5 | I8: =INDEX('Реестр рисков'!$A$9:$A$25,MATCH(3,'Реестр рисков'!$T$9:$T$25,0))&". "&INDEX('Реестр рисков'!$C$9:$C$25,MATCH(3,'Реестр рисков'!$T$9:$T$25,0)) -> Р1. Неполные и меняющиеся требования | J8: =INDEX('Реестр рисков'!$K$9:$K$25,MATCH(3,'Реестр рисков'!$T$9:$T$25,0)) -> 12 | K8: =INDEX('Реестр рисков'!$L$9:$L$25,MATCH(3,'Реестр рисков'!$T$9:$T$25,0)) -> Высокий | L8: =INDEX('Реестр рисков'!$P$9:$P$25,MATCH(3,'Реестр рисков'!$T$9:$T$25,0)) -> Паноченко В.В.
A9: 1 | B9: очень низкая | C9: =TRIM(IF(AND('Реестр рисков'!$I$9=1,'Реестр рисков'!$J$9=1),'Реестр рисков'!$A$9&" ","")&IF(AND('Реестр рисков'!$I$10=1,'Реестр рисков'!$J$10=1),'Реестр рисков'!$A$10&" ","")&IF(AND('Реестр рисков'!$I$11=1,'Реестр рисков'!$J$11=1),'Реестр рисков'!$A$11&" ","")&IF(AND('Реестр рисков'!$I$12=1,'Реестр рисков'!$J$12=1),'Реестр рисков'!$A$12&" ","")&IF(AND('Реестр рисков'!$I$13=1,'Реестр рисков'!$J$13=1),'Реестр рисков'!$A$13&" ","")&IF(AND('Реестр рисков'!$I$14=1,'Реестр рисков'!$J$14=1),'Реестр рисков'!$A$14&" ","")&IF(AND('Реестр рисков'!$I$15=1,'Реестр рисков'!$J$15=1),'Реестр рисков'!$A$15&" ","")&IF(AND('Реестр рисков'!$I$16=1,'Реестр рисков'!$J$16=1),'Реестр рисков'!$A$16&" ","")&IF(AND('Реестр рисков'!$I$17=1,'Реестр рисков'!$J$17=1),'Реестр рисков'!$A$17&" ","")&IF(AND('Реестр рисков'!$I$18=1,'Реестр рисков'!$J$18=1),'Реестр рисков'!$A$18&" ","")&IF(AND('Реестр рисков'!$I$19=1,'Реестр рисков'!$J$19=1),'Реестр рисков'!$A$19&" ","")&IF(AND('Реестр рисков'!$I$20=1,'Реестр рисков'!$J$20=1),'Реестр рисков'!$A$20&" ","")&IF(AND('Реестр рисков'!$I$21=1,'Реестр рисков'!$J$21=1),'Реестр рисков'!$A$21&" ","")&IF(AND('Реестр рисков'!$I$22=1,'Реестр рисков'!$J$22=1),'Реестр рисков'!$A$22&" ","")&IF(AND('Реестр рисков'!$I$23=1,'Реестр рисков'!$J$23=1),'Реестр рисков'!$A$23&" ","")&IF(AND('Реестр рисков'!$I$24=1,'Реестр рисков'!$J$24=1),'Реестр рисков'!$A$24&" ","")&IF(AND('Реестр рисков'!$I$25=1,'Реестр рисков'!$J$25=1),'Реестр рисков'!$A$25&" ","")) | D9: =TRIM(IF(AND('Реестр рисков'!$I$9=1,'Реестр рисков'!$J$9=2),'Реестр рисков'!$A$9&" ","")&IF(AND('Реестр рисков'!$I$10=1,'Реестр рисков'!$J$10=2),'Реестр рисков'!$A$10&" ","")&IF(AND('Реестр рисков'!$I$11=1,'Реестр рисков'!$J$11=2),'Реестр рисков'!$A$11&" ","")&IF(AND('Реестр рисков'!$I$12=1,'Реестр рисков'!$J$12=2),'Реестр рисков'!$A$12&" ","")&IF(AND('Реестр рисков'!$I$13=1,'Реестр рисков'!$J$13=2),'Реестр рисков'!$A$13&" ","")&IF(AND('Реестр рисков'!$I$14=1,'Реестр рисков'!$J$14=2),'Реестр рисков'!$A$14&" ","")&IF(AND('Реестр рисков'!$I$15=1,'Реестр рисков'!$J$15=2),'Реестр рисков'!$A$15&" ","")&IF(AND('Реестр рисков'!$I$16=1,'Реестр рисков'!$J$16=2),'Реестр рисков'!$A$16&" ","")&IF(AND('Реестр рисков'!$I$17=1,'Реестр рисков'!$J$17=2),'Реестр рисков'!$A$17&" ","")&IF(AND('Реестр рисков'!$I$18=1,'Реестр рисков'!$J$18=2),'Реестр рисков'!$A$18&" ","")&IF(AND('Реестр рисков'!$I$19=1,'Реестр рисков'!$J$19=2),'Реестр рисков'!$A$19&" ","")&IF(AND('Реестр рисков'!$I$20=1,'Реестр рисков'!$J$20=2),'Реестр рисков'!$A$20&" ","")&IF(AND('Реестр рисков'!$I$21=1,'Реестр рисков'!$J$21=2),'Реестр рисков'!$A$21&" ","")&IF(AND('Реестр рисков'!$I$22=1,'Реестр рисков'!$J$22=2),'Реестр рисков'!$A$22&" ","")&IF(AND('Реестр рисков'!$I$23=1,'Реестр рисков'!$J$23=2),'Реестр рисков'!$A$23&" ","")&IF(AND('Реестр рисков'!$I$24=1,'Реестр рисков'!$J$24=2),'Реестр рисков'!$A$24&" ","")&IF(AND('Реестр рисков'!$I$25=1,'Реестр рисков'!$J$25=2),'Реестр рисков'!$A$25&" ","")) | E9: =TRIM(IF(AND('Реестр рисков'!$I$9=1,'Реестр рисков'!$J$9=3),'Реестр рисков'!$A$9&" ","")&IF(AND('Реестр рисков'!$I$10=1,'Реестр рисков'!$J$10=3),'Реестр рисков'!$A$10&" ","")&IF(AND('Реестр рисков'!$I$11=1,'Реестр рисков'!$J$11=3),'Реестр рисков'!$A$11&" ","")&IF(AND('Реестр рисков'!$I$12=1,'Реестр рисков'!$J$12=3),'Реестр рисков'!$A$12&" ","")&IF(AND('Реестр рисков'!$I$13=1,'Реестр рисков'!$J$13=3),'Реестр рисков'!$A$13&" ","")&IF(AND('Реестр рисков'!$I$14=1,'Реестр рисков'!$J$14=3),'Реестр рисков'!$A$14&" ","")&IF(AND('Реестр рисков'!$I$15=1,'Реестр рисков'!$J$15=3),'Реестр рисков'!$A$15&" ","")&IF(AND('Реестр рисков'!$I$16=1,'Реестр рисков'!$J$16=3),'Реестр рисков'!$A$16&" ","")&IF(AND('Реестр рисков'!$I$17=1,'Реестр рисков'!$J$17=3),'Реестр рисков'!$A$17&" ","")&IF(AND('Реестр рисков'!$I$18=1,'Реестр рисков'!$J$18=3),'Реестр рисков'!$A$18&" ","")&IF(AND('Реестр рисков'!$I$19=1,'Реестр рисков'!$J$19=3),'Реестр рисков'!$A$19&" ","")&IF(AND('Реестр рисков'!$I$20=1,'Реестр рисков'!$J$20=3),'Реестр рисков'!$A$20&" ","")&IF(AND('Реестр рисков'!$I$21=1,'Реестр рисков'!$J$21=3),'Реестр рисков'!$A$21&" ","")&IF(AND('Реестр рисков'!$I$22=1,'Реестр рисков'!$J$22=3),'Реестр рисков'!$A$22&" ","")&IF(AND('Реестр рисков'!$I$23=1,'Реестр рисков'!$J$23=3),'Реестр рисков'!$A$23&" ","")&IF(AND('Реестр рисков'!$I$24=1,'Реестр рисков'!$J$24=3),'Реестр рисков'!$A$24&" ","")&IF(AND('Реестр рисков'!$I$25=1,'Реестр рисков'!$J$25=3),'Реестр рисков'!$A$25&" ","")) | F9: =TRIM(IF(AND('Реестр рисков'!$I$9=1,'Реестр рисков'!$J$9=4),'Реестр рисков'!$A$9&" ","")&IF(AND('Реестр рисков'!$I$10=1,'Реестр рисков'!$J$10=4),'Реестр рисков'!$A$10&" ","")&IF(AND('Реестр рисков'!$I$11=1,'Реестр рисков'!$J$11=4),'Реестр рисков'!$A$11&" ","")&IF(AND('Реестр рисков'!$I$12=1,'Реестр рисков'!$J$12=4),'Реестр рисков'!$A$12&" ","")&IF(AND('Реестр рисков'!$I$13=1,'Реестр рисков'!$J$13=4),'Реестр рисков'!$A$13&" ","")&IF(AND('Реестр рисков'!$I$14=1,'Реестр рисков'!$J$14=4),'Реестр рисков'!$A$14&" ","")&IF(AND('Реестр рисков'!$I$15=1,'Реестр рисков'!$J$15=4),'Реестр рисков'!$A$15&" ","")&IF(AND('Реестр рисков'!$I$16=1,'Реестр рисков'!$J$16=4),'Реестр рисков'!$A$16&" ","")&IF(AND('Реестр рисков'!$I$17=1,'Реестр рисков'!$J$17=4),'Реестр рисков'!$A$17&" ","")&IF(AND('Реестр рисков'!$I$18=1,'Реестр рисков'!$J$18=4),'Реестр рисков'!$A$18&" ","")&IF(AND('Реестр рисков'!$I$19=1,'Реестр рисков'!$J$19=4),'Реестр рисков'!$A$19&" ","")&IF(AND('Реестр рисков'!$I$20=1,'Реестр рисков'!$J$20=4),'Реестр рисков'!$A$20&" ","")&IF(AND('Реестр рисков'!$I$21=1,'Реестр рисков'!$J$21=4),'Реестр рисков'!$A$21&" ","")&IF(AND('Реестр рисков'!$I$22=1,'Реестр рисков'!$J$22=4),'Реестр рисков'!$A$22&" ","")&IF(AND('Реестр рисков'!$I$23=1,'Реестр рисков'!$J$23=4),'Реестр рисков'!$A$23&" ","")&IF(AND('Реестр рисков'!$I$24=1,'Реестр рисков'!$J$24=4),'Реестр рисков'!$A$24&" ","")&IF(AND('Реестр рисков'!$I$25=1,'Реестр рисков'!$J$25=4),'Реестр рисков'!$A$25&" ","")) -> Р14 | G9: =TRIM(IF(AND('Реестр рисков'!$I$9=1,'Реестр рисков'!$J$9=5),'Реестр рисков'!$A$9&" ","")&IF(AND('Реестр рисков'!$I$10=1,'Реестр рисков'!$J$10=5),'Реестр рисков'!$A$10&" ","")&IF(AND('Реестр рисков'!$I$11=1,'Реестр рисков'!$J$11=5),'Реестр рисков'!$A$11&" ","")&IF(AND('Реестр рисков'!$I$12=1,'Реестр рисков'!$J$12=5),'Реестр рисков'!$A$12&" ","")&IF(AND('Реестр рисков'!$I$13=1,'Реестр рисков'!$J$13=5),'Реестр рисков'!$A$13&" ","")&IF(AND('Реестр рисков'!$I$14=1,'Реестр рисков'!$J$14=5),'Реестр рисков'!$A$14&" ","")&IF(AND('Реестр рисков'!$I$15=1,'Реестр рисков'!$J$15=5),'Реестр рисков'!$A$15&" ","")&IF(AND('Реестр рисков'!$I$16=1,'Реестр рисков'!$J$16=5),'Реестр рисков'!$A$16&" ","")&IF(AND('Реестр рисков'!$I$17=1,'Реестр рисков'!$J$17=5),'Реестр рисков'!$A$17&" ","")&IF(AND('Реестр рисков'!$I$18=1,'Реестр рисков'!$J$18=5),'Реестр рисков'!$A$18&" ","")&IF(AND('Реестр рисков'!$I$19=1,'Реестр рисков'!$J$19=5),'Реестр рисков'!$A$19&" ","")&IF(AND('Реестр рисков'!$I$20=1,'Реестр рисков'!$J$20=5),'Реестр рисков'!$A$20&" ","")&IF(AND('Реестр рисков'!$I$21=1,'Реестр рисков'!$J$21=5),'Реестр рисков'!$A$21&" ","")&IF(AND('Реестр рисков'!$I$22=1,'Реестр рисков'!$J$22=5),'Реестр рисков'!$A$22&" ","")&IF(AND('Реестр рисков'!$I$23=1,'Реестр рисков'!$J$23=5),'Реестр рисков'!$A$23&" ","")&IF(AND('Реестр рисков'!$I$24=1,'Реестр рисков'!$J$24=5),'Реестр рисков'!$A$24&" ","")&IF(AND('Реестр рисков'!$I$25=1,'Реестр рисков'!$J$25=5),'Реестр рисков'!$A$25&" ","")) | I9: =INDEX('Реестр рисков'!$A$9:$A$25,MATCH(4,'Реестр рисков'!$T$9:$T$25,0))&". "&INDEX('Реестр рисков'!$C$9:$C$25,MATCH(4,'Реестр рисков'!$T$9:$T$25,0)) -> Р8. Превышение плановой трудоёмкости и стоимости | J9: =INDEX('Реестр рисков'!$K$9:$K$25,MATCH(4,'Реестр рисков'!$T$9:$T$25,0)) -> 12 | K9: =INDEX('Реестр рисков'!$L$9:$L$25,MATCH(4,'Реестр рисков'!$T$9:$T$25,0)) -> Высокий | L9: =INDEX('Реестр рисков'!$P$9:$P$25,MATCH(4,'Реестр рисков'!$T$9:$T$25,0)) -> Лопатин Д.И.
I10: =INDEX('Реестр рисков'!$A$9:$A$25,MATCH(5,'Реестр рисков'!$T$9:$T$25,0))&". "&INDEX('Реестр рисков'!$C$9:$C$25,MATCH(5,'Реестр рисков'!$T$9:$T$25,0)) -> Р10. Разногласия по приёмке | J10: =INDEX('Реестр рисков'!$K$9:$K$25,MATCH(5,'Реестр рисков'!$T$9:$T$25,0)) -> 12 | K10: =INDEX('Реестр рисков'!$L$9:$L$25,MATCH(5,'Реестр рисков'!$T$9:$T$25,0)) -> Высокий | L10: =INDEX('Реестр рисков'!$P$9:$P$25,MATCH(5,'Реестр рисков'!$T$9:$T$25,0)) -> Сибирко И.С.
I11: =INDEX('Реестр рисков'!$A$9:$A$25,MATCH(6,'Реестр рисков'!$T$9:$T$25,0))&". "&INDEX('Реестр рисков'!$C$9:$C$25,MATCH(6,'Реестр рисков'!$T$9:$T$25,0)) -> Р12. Один разработчик серверной части на критической цепочке | J11: =INDEX('Реестр рисков'!$K$9:$K$25,MATCH(6,'Реестр рисков'!$T$9:$T$25,0)) -> 12 | K11: =INDEX('Реестр рисков'!$L$9:$L$25,MATCH(6,'Реестр рисков'!$T$9:$T$25,0)) -> Высокий | L11: =INDEX('Реестр рисков'!$P$9:$P$25,MATCH(6,'Реестр рисков'!$T$9:$T$25,0)) -> Горбов Н.В.
A12: Распределение по категориям | I12: =INDEX('Реестр рисков'!$A$9:$A$25,MATCH(7,'Реестр рисков'!$T$9:$T$25,0))&". "&INDEX('Реестр рисков'!$C$9:$C$25,MATCH(7,'Реестр рисков'!$T$9:$T$25,0)) -> Р5. Срыв финальной приёмки 26.12.2026 | J12: =INDEX('Реестр рисков'!$K$9:$K$25,MATCH(7,'Реестр рисков'!$T$9:$T$25,0)) -> 10 | K12: =INDEX('Реестр рисков'!$L$9:$L$25,MATCH(7,'Реестр рисков'!$T$9:$T$25,0)) -> Средний | L12: =INDEX('Реестр рисков'!$P$9:$P$25,MATCH(7,'Реестр рисков'!$T$9:$T$25,0)) -> Лопатин Д.И.
A13: Категория | C13: Высокий | D13: Средний | E13: Низкий | F13: Всего | G13: Сумма баллов | I13: =INDEX('Реестр рисков'!$A$9:$A$25,MATCH(8,'Реестр рисков'!$T$9:$T$25,0))&". "&INDEX('Реестр рисков'!$C$9:$C$25,MATCH(8,'Реестр рисков'!$T$9:$T$25,0)) -> Р2. Правила совместимости и готовности кобылы получены поздно или неверно | J13: =INDEX('Реестр рисков'!$K$9:$K$25,MATCH(8,'Реестр рисков'!$T$9:$T$25,0)) -> 9 | K13: =INDEX('Реестр рисков'!$L$9:$L$25,MATCH(8,'Реестр рисков'!$T$9:$T$25,0)) -> Средний | L13: =INDEX('Реестр рисков'!$P$9:$P$25,MATCH(8,'Реестр рисков'!$T$9:$T$25,0)) -> Лопатин Д.И.
A14: Требования и содержание | C14: =COUNTIFS('Реестр рисков'!$B$9:$B$25,$A14,'Реестр рисков'!$L$9:$L$25,"Высокий") -> 1 | D14: =COUNTIFS('Реестр рисков'!$B$9:$B$25,$A14,'Реестр рисков'!$L$9:$L$25,"Средний") -> 3 | E14: =COUNTIFS('Реестр рисков'!$B$9:$B$25,$A14,'Реестр рисков'!$L$9:$L$25,"Низкий") -> 0 | F14: =SUM(C14:E14) -> 4 | G14: =SUMIF('Реестр рисков'!$B$9:$B$25,$A14,'Реестр рисков'!$K$9:$K$25) -> 35 | I14: =INDEX('Реестр рисков'!$A$9:$A$25,MATCH(9,'Реестр рисков'!$T$9:$T$25,0))&". "&INDEX('Реестр рисков'!$C$9:$C$25,MATCH(9,'Реестр рисков'!$T$9:$T$25,0)) -> Р6. Расширение ожиданий за границы проекта («система на вырост») | J14: =INDEX('Реестр рисков'!$K$9:$K$25,MATCH(9,'Реестр рисков'!$T$9:$T$25,0)) -> 9 | K14: =INDEX('Реестр рисков'!$L$9:$L$25,MATCH(9,'Реестр рисков'!$T$9:$T$25,0)) -> Средний | L14: =INDEX('Реестр рисков'!$P$9:$P$25,MATCH(9,'Реестр рисков'!$T$9:$T$25,0)) -> Лопатин Д.И.
A15: Предметная область | C15: =COUNTIFS('Реестр рисков'!$B$9:$B$25,$A15,'Реестр рисков'!$L$9:$L$25,"Высокий") -> 0 | D15: =COUNTIFS('Реестр рисков'!$B$9:$B$25,$A15,'Реестр рисков'!$L$9:$L$25,"Средний") -> 1 | E15: =COUNTIFS('Реестр рисков'!$B$9:$B$25,$A15,'Реестр рисков'!$L$9:$L$25,"Низкий") -> 1 | F15: =SUM(C15:E15) -> 2 | G15: =SUMIF('Реестр рисков'!$B$9:$B$25,$A15,'Реестр рисков'!$K$9:$K$25) -> 13 | I15: =INDEX('Реестр рисков'!$A$9:$A$25,MATCH(10,'Реестр рисков'!$T$9:$T$25,0))&". "&INDEX('Реестр рисков'!$C$9:$C$25,MATCH(10,'Реестр рисков'!$T$9:$T$25,0)) -> Р13. Сложность освоения инструментов и лимиты бесплатных тарифов | J15: =INDEX('Реестр рисков'!$K$9:$K$25,MATCH(10,'Реестр рисков'!$T$9:$T$25,0)) -> 9 | K15: =INDEX('Реестр рисков'!$L$9:$L$25,MATCH(10,'Реестр рисков'!$T$9:$T$25,0)) -> Средний | L15: =INDEX('Реестр рисков'!$P$9:$P$25,MATCH(10,'Реестр рисков'!$T$9:$T$25,0)) -> Горбов Н.В.
A16: Регуляторные | C16: =COUNTIFS('Реестр рисков'!$B$9:$B$25,$A16,'Реестр рисков'!$L$9:$L$25,"Высокий") -> 0 | D16: =COUNTIFS('Реестр рисков'!$B$9:$B$25,$A16,'Реестр рисков'!$L$9:$L$25,"Средний") -> 1 | E16: =COUNTIFS('Реестр рисков'!$B$9:$B$25,$A16,'Реестр рисков'!$L$9:$L$25,"Низкий") -> 1 | F16: =SUM(C16:E16) -> 2 | G16: =SUMIF('Реестр рисков'!$B$9:$B$25,$A16,'Реестр рисков'!$K$9:$K$25) -> 10 | I16: =INDEX('Реестр рисков'!$A$9:$A$25,MATCH(11,'Реестр рисков'!$T$9:$T$25,0))&". "&INDEX('Реестр рисков'!$C$9:$C$25,MATCH(11,'Реестр рисков'!$T$9:$T$25,0)) -> Р3. Недостаточно данных для справок, не определено понятие «контакт» | J16: =INDEX('Реестр рисков'!$K$9:$K$25,MATCH(11,'Реестр рисков'!$T$9:$T$25,0)) -> 8 | K16: =INDEX('Реестр рисков'!$L$9:$L$25,MATCH(11,'Реестр рисков'!$T$9:$T$25,0)) -> Средний | L16: =INDEX('Реестр рисков'!$P$9:$P$25,MATCH(11,'Реестр рисков'!$T$9:$T$25,0)) -> Паноченко В.В.
A17: Сроки | C17: =COUNTIFS('Реестр рисков'!$B$9:$B$25,$A17,'Реестр рисков'!$L$9:$L$25,"Высокий") -> 0 | D17: =COUNTIFS('Реестр рисков'!$B$9:$B$25,$A17,'Реестр рисков'!$L$9:$L$25,"Средний") -> 1 | E17: =COUNTIFS('Реестр рисков'!$B$9:$B$25,$A17,'Реестр рисков'!$L$9:$L$25,"Низкий") -> 0 | F17: =SUM(C17:E17) -> 1 | G17: =SUMIF('Реестр рисков'!$B$9:$B$25,$A17,'Реестр рисков'!$K$9:$K$25) -> 10 | I17: =INDEX('Реестр рисков'!$A$9:$A$25,MATCH(12,'Реестр рисков'!$T$9:$T$25,0))&". "&INDEX('Реестр рисков'!$C$9:$C$25,MATCH(12,'Реестр рисков'!$T$9:$T$25,0)) -> Р15. Визуальный стиль не принят заказчиком | J17: =INDEX('Реестр рисков'!$K$9:$K$25,MATCH(12,'Реестр рисков'!$T$9:$T$25,0)) -> 6 | K17: =INDEX('Реестр рисков'!$L$9:$L$25,MATCH(12,'Реестр рисков'!$T$9:$T$25,0)) -> Средний | L17: =INDEX('Реестр рисков'!$P$9:$P$25,MATCH(12,'Реестр рисков'!$T$9:$T$25,0)) -> Кодинцев А.В.
A18: Ресурсы (команда) | C18: =COUNTIFS('Реестр рисков'!$B$9:$B$25,$A18,'Реестр рисков'!$L$9:$L$25,"Высокий") -> 2 | D18: =COUNTIFS('Реестр рисков'!$B$9:$B$25,$A18,'Реестр рисков'!$L$9:$L$25,"Средний") -> 0 | E18: =COUNTIFS('Реестр рисков'!$B$9:$B$25,$A18,'Реестр рисков'!$L$9:$L$25,"Низкий") -> 0 | F18: =SUM(C18:E18) -> 2 | G18: =SUMIF('Реестр рисков'!$B$9:$B$25,$A18,'Реестр рисков'!$K$9:$K$25) -> 28 | I18: =INDEX('Реестр рисков'!$A$9:$A$25,MATCH(13,'Реестр рисков'!$T$9:$T$25,0))&". "&INDEX('Реестр рисков'!$C$9:$C$25,MATCH(13,'Реестр рисков'!$T$9:$T$25,0)) -> Р16. Регулятор меняет или ужесточает требования к справкам | J18: =INDEX('Реестр рисков'!$K$9:$K$25,MATCH(13,'Реестр рисков'!$T$9:$T$25,0)) -> 6 | K18: =INDEX('Реестр рисков'!$L$9:$L$25,MATCH(13,'Реестр рисков'!$T$9:$T$25,0)) -> Средний | L18: =INDEX('Реестр рисков'!$P$9:$P$25,MATCH(13,'Реестр рисков'!$T$9:$T$25,0)) -> Паноченко В.В.
A19: Стоимость | C19: =COUNTIFS('Реестр рисков'!$B$9:$B$25,$A19,'Реестр рисков'!$L$9:$L$25,"Высокий") -> 1 | D19: =COUNTIFS('Реестр рисков'!$B$9:$B$25,$A19,'Реестр рисков'!$L$9:$L$25,"Средний") -> 0 | E19: =COUNTIFS('Реестр рисков'!$B$9:$B$25,$A19,'Реестр рисков'!$L$9:$L$25,"Низкий") -> 0 | F19: =SUM(C19:E19) -> 1 | G19: =SUMIF('Реестр рисков'!$B$9:$B$25,$A19,'Реестр рисков'!$K$9:$K$25) -> 12 | I19: =INDEX('Реестр рисков'!$A$9:$A$25,MATCH(14,'Реестр рисков'!$T$9:$T$25,0))&". "&INDEX('Реестр рисков'!$C$9:$C$25,MATCH(14,'Реестр рисков'!$T$9:$T$25,0)) -> Р4. Поля реестра не соответствуют требованиям породной ассоциации и учёта поголовья | J19: =INDEX('Реестр рисков'!$K$9:$K$25,MATCH(14,'Реестр рисков'!$T$9:$T$25,0)) -> 4 | K19: =INDEX('Реестр рисков'!$L$9:$L$25,MATCH(14,'Реестр рисков'!$T$9:$T$25,0)) -> Низкий | L19: =INDEX('Реестр рисков'!$P$9:$P$25,MATCH(14,'Реестр рисков'!$T$9:$T$25,0)) -> Паноченко В.В.
A20: Организационные | C20: =COUNTIFS('Реестр рисков'!$B$9:$B$25,$A20,'Реестр рисков'!$L$9:$L$25,"Высокий") -> 2 | D20: =COUNTIFS('Реестр рисков'!$B$9:$B$25,$A20,'Реестр рисков'!$L$9:$L$25,"Средний") -> 0 | E20: =COUNTIFS('Реестр рисков'!$B$9:$B$25,$A20,'Реестр рисков'!$L$9:$L$25,"Низкий") -> 0 | F20: =SUM(C20:E20) -> 2 | G20: =SUMIF('Реестр рисков'!$B$9:$B$25,$A20,'Реестр рисков'!$K$9:$K$25) -> 27 | I20: =INDEX('Реестр рисков'!$A$9:$A$25,MATCH(15,'Реестр рисков'!$T$9:$T$25,0))&". "&INDEX('Реестр рисков'!$C$9:$C$25,MATCH(15,'Реестр рисков'!$T$9:$T$25,0)) -> Р9. Задержка или пропуски данных ветеринара | J20: =INDEX('Реестр рисков'!$K$9:$K$25,MATCH(15,'Реестр рисков'!$T$9:$T$25,0)) -> 4 | K20: =INDEX('Реестр рисков'!$L$9:$L$25,MATCH(15,'Реестр рисков'!$T$9:$T$25,0)) -> Низкий | L20: =INDEX('Реестр рисков'!$P$9:$P$25,MATCH(15,'Реестр рисков'!$T$9:$T$25,0)) -> Паноченко В.В.
A21: Технические | C21: =COUNTIFS('Реестр рисков'!$B$9:$B$25,$A21,'Реестр рисков'!$L$9:$L$25,"Высокий") -> 0 | D21: =COUNTIFS('Реестр рисков'!$B$9:$B$25,$A21,'Реестр рисков'!$L$9:$L$25,"Средний") -> 1 | E21: =COUNTIFS('Реестр рисков'!$B$9:$B$25,$A21,'Реестр рисков'!$L$9:$L$25,"Низкий") -> 1 | F21: =SUM(C21:E21) -> 2 | G21: =SUMIF('Реестр рисков'!$B$9:$B$25,$A21,'Реестр рисков'!$K$9:$K$25) -> 13 | I21: =INDEX('Реестр рисков'!$A$9:$A$25,MATCH(16,'Реестр рисков'!$T$9:$T$25,0))&". "&INDEX('Реестр рисков'!$C$9:$C$25,MATCH(16,'Реестр рисков'!$T$9:$T$25,0)) -> Р14. Потеря данных или недоступность репозитория и демостенда | J21: =INDEX('Реестр рисков'!$K$9:$K$25,MATCH(16,'Реестр рисков'!$T$9:$T$25,0)) -> 4 | K21: =INDEX('Реестр рисков'!$L$9:$L$25,MATCH(16,'Реестр рисков'!$T$9:$T$25,0)) -> Низкий | L21: =INDEX('Реестр рисков'!$P$9:$P$25,MATCH(16,'Реестр рисков'!$T$9:$T$25,0)) -> Шунулин Р.А.
A22: Рыночные (бизнес) | C22: =COUNTIFS('Реестр рисков'!$B$9:$B$25,$A22,'Реестр рисков'!$L$9:$L$25,"Высокий") -> 0 | D22: =COUNTIFS('Реестр рисков'!$B$9:$B$25,$A22,'Реестр рисков'!$L$9:$L$25,"Средний") -> 0 | E22: =COUNTIFS('Реестр рисков'!$B$9:$B$25,$A22,'Реестр рисков'!$L$9:$L$25,"Низкий") -> 1 | F22: =SUM(C22:E22) -> 1 | G22: =SUMIF('Реестр рисков'!$B$9:$B$25,$A22,'Реестр рисков'!$K$9:$K$25) -> 4 | I22: =INDEX('Реестр рисков'!$A$9:$A$25,MATCH(17,'Реестр рисков'!$T$9:$T$25,0))&". "&INDEX('Реестр рисков'!$C$9:$C$25,MATCH(17,'Реестр рисков'!$T$9:$T$25,0)) -> Р17. Конкуренты запускают удобную онлайн-запись | J22: =INDEX('Реестр рисков'!$K$9:$K$25,MATCH(17,'Реестр рисков'!$T$9:$T$25,0)) -> 4 | K22: =INDEX('Реестр рисков'!$L$9:$L$25,MATCH(17,'Реестр рисков'!$T$9:$T$25,0)) -> Низкий | L22: =INDEX('Реестр рисков'!$P$9:$P$25,MATCH(17,'Реестр рисков'!$T$9:$T$25,0)) -> Нгуен Д.В.
A23: Итого | C23: =SUM(C14:C22) -> 6 | D23: =SUM(D14:D22) -> 7 | E23: =SUM(E14:E22) -> 4 | F23: =SUM(F14:F22) -> 17 | G23: =SUM(G14:G22) -> 152

Sheet Количественная оценка
A1: Количественная оценка: ожидаемые потери и резерв
A2: Ожидаемые потери = расчётная вероятность (шкала P на листе «Методика») × потери при наступлении × ставка. Потери в часах — экспертная оценка владельца риска со сверкой по оценкам пакетов ИСР.
A4: Средняя ставка, USD/ч | C4: 55 | D4: сводная таблица оценок (как в книге PERT)
A6: № | B6: Риск | C6: P (балл) | D6: Вероятность | E6: Потери при наступлении, ч | F6: Обоснование потерь | G6: Ожидаемые потери, ч | H6: Ожидаемые потери, USD | I6: Покрывается резервом
A7: ='Реестр рисков'!A9 -> Р1 | B7: ='Реестр рисков'!C9 -> Неполные и меняющиеся требования | C7: ='Реестр рисков'!I9 -> 4 | D7: =INDEX(Методика!$D$5:$D$9,C7) -> 0.6 | E7: 30 | F7: Переделка 2–3 экранов с логикой, ≈10 ч каждый | G7: =D7*E7 -> 18 | H7: =G7*$C$4 -> 990 | I7: да
A8: ='Реестр рисков'!A10 -> Р2 | B8: ='Реестр рисков'!C10 -> Правила совместимости и готовности кобылы получены поздно или неверно | C8: ='Реестр рисков'!I10 -> 3 | D8: =INDEX(Методика!$D$5:$D$9,C8) -> 0.4 | E8: 20 | F8: Доработка 4.2 под новую таблицу правил + повтор 4.1 | G8: =D8*E8 -> 8 | H8: =G8*$C$4 -> 440 | I8: да
A9: ='Реестр рисков'!A11 -> Р3 | B9: ='Реестр рисков'!C11 -> Недостаточно данных для справок, не определено понятие «контакт» | C9: ='Реестр рисков'!I11 -> 2 | D9: =INDEX(Методика!$D$5:$D$9,C9) -> 0.2 | E9: 40 | F9: Доработка 3.4, 3.5 и демоданных (≈ E пакета 3.5 + 12 ч) | G9: =D9*E9 -> 8 | H9: =G9*$C$4 -> 440 | I9: да
A10: ='Реестр рисков'!A12 -> Р4 | B10: ='Реестр рисков'!C12 -> Поля реестра не соответствуют требованиям породной ассоциации и учёта поголовья | C10: ='Реестр рисков'!I12 -> 2 | D10: =INDEX(Методика!$D$5:$D$9,C10) -> 0.2 | E10: 10 | F10: Новые поля карточки и формы выгрузки | G10: =D10*E10 -> 2 | H10: =G10*$C$4 -> 110 | I10: да
A11: ='Реестр рисков'!A13 -> Р5 | B11: ='Реестр рисков'!C13 -> Срыв финальной приёмки 26.12.2026 | C11: ='Реестр рисков'!I13 -> 2 | D11: =INDEX(Методика!$D$5:$D$9,C11) -> 0.2 | E11: 40 | F11: Работа команды в резерве 26–31.12 и сверх плана на цепочке | G11: =D11*E11 -> 8 | H11: =G11*$C$4 -> 440 | I11: да
A12: ='Реестр рисков'!A14 -> Р6 | B12: ='Реестр рисков'!C14 -> Расширение ожиданий за границы проекта («система на вырост») | C12: ='Реестр рисков'!I14 -> 3 | D12: =INDEX(Методика!$D$5:$D$9,C12) -> 0.4 | E12: 16 | F12: Анализ и частичная реализация двух запросов по 8 ч | G12: =D12*E12 -> 6.4 | H12: =G12*$C$4 -> 352 | I12: да
A13: ='Реестр рисков'!A15 -> Р7 | B13: ='Реестр рисков'!C15 -> Нехватка времени участников из-за учёбы | C13: ='Реестр рисков'!I15 -> 4 | D13: =INDEX(Методика!$D$5:$D$9,C13) -> 0.6 | E13: 40 | F13: Недоработка двух участников по 10 ч/нед в течение 2 недель | G13: =D13*E13 -> 24 | H13: =G13*$C$4 -> 1320 | I13: да
A14: ='Реестр рисков'!A16 -> Р8 | B14: ='Реестр рисков'!C16 -> Превышение плановой трудоёмкости и стоимости | C14: ='Реестр рисков'!I16 -> 3 | D14: =INDEX(Методика!$D$5:$D$9,C14) -> 0.4 | E14: 55 | F14: 10% остатка работ варианта Б (546,6 ч) | G14: =D14*E14 -> 22 | H14: =G14*$C$4 -> 1210 | I14: да
A15: ='Реестр рисков'!A17 -> Р9 | B15: ='Реестр рисков'!C17 -> Задержка или пропуски данных ветеринара | C15: ='Реестр рисков'!I17 -> 2 | D15: =INDEX(Методика!$D$5:$D$9,C15) -> 0.2 | E15: 8 | F15: Уточнение правил готовности и формы ввода | G15: =D15*E15 -> 1.6 | H15: =G15*$C$4 -> 88 | I15: да
A16: ='Реестр рисков'!A18 -> Р10 | B16: ='Реестр рисков'!C18 -> Разногласия по приёмке | C16: ='Реестр рисков'!I18 -> 3 | D16: =INDEX(Методика!$D$5:$D$9,C16) -> 0.4 | E16: 16 | F16: Повторная доработка и проверка 2 критериев | G16: =D16*E16 -> 6.4 | H16: =G16*$C$4 -> 352 | I16: да
A17: ='Реестр рисков'!A19 -> Р11 | B17: ='Реестр рисков'!C19 -> Запрос на изменение № 1 не согласован | C17: ='Реестр рисков'!I19 -> 3 | D17: =INDEX(Методика!$D$5:$D$9,C17) -> 0.4 | E17: 71 | F17: Дефицит при 54 ч/нед: 6,6 раб. дн × 54 ч / 5 ≈ 71 ч | G17: =D17*E17 -> 28.4 | H17: =G17*$C$4 -> 1562 | I17: нет
A18: ='Реестр рисков'!A20 -> Р12 | B18: ='Реестр рисков'!C20 -> Один разработчик серверной части на критической цепочке | C18: ='Реестр рисков'!I20 -> 3 | D18: =INDEX(Методика!$D$5:$D$9,C18) -> 0.4 | E18: 40 | F18: 16 ч работы бэкенда × 2 (замена медленнее) + 8 ч ввода в задачи | G18: =D18*E18 -> 16 | H18: =G18*$C$4 -> 880 | I18: да
... A23: ='Реестр рисков'!A25 -> Р17 | B23: ='Реестр рисков'!C25 -> Конкуренты запускают удобную онлайн-запись | C23: ='Реестр рисков'!I25 -> 2 | D23: =INDEX(Методика!$D$5:$D$9,C23) -> 0.2 | E23: 17 | F23: E пакета 5.2 = 16,7 ч | G23: =D23*E23 -> 3.4 | H23: =G23*$C$4 -> 187 | I23: да
A24: Итого | E24: =SUM(E7:E23) -> 481 | G24: =SUM(G7:G23) -> 169.4 | H24: =SUM(H7:H23) -> 9317
A25: в т.ч. покрывается резервом | G25: =SUMIF(I7:I23,"да",G7:G23) -> 141 | H25: =SUMIF(I7:I23,"да",H7:H23) -> 7755
A26: Р11 резервом не покрывается: он решается составом объёма (запрос на изменение № 1), а не деньгами. Риски частично пересекаются (Р5 с Р7 и Р12), поэтому сумма — верхняя оценка.
A28: Сверка с резервом и фондом времени (вариант Б)
B29: Показатель | C29: Значение | E29: Источник / формула
A30: 1 | B30: Стоимость работ (BAC), USD | C30: 34706 | E30: Книга «Расписание», лист «Вехи»: BAC варианта Б
A31: 2 | B31: Доля резерва на риски | C31: 0.1 | E31: Устав, п. 3.2
A32: 3 | B32: Резерв на риски, USD | C32: =C30*C31 -> 3470.6 | E32: стр. 1 × стр. 2
A33: 4 | B33: Ожидаемые потери (покрываемые резервом), USD | C33: =H25 -> 7755 | E33: итог таблицы выше
A34: 5 | B34: Покрытие ожидаемых потерь резервом | C34: =C32/C33 -> 0.44753063 | E34: стр. 3 / стр. 4
A35: 6 | B35: Потолок бюджета, USD | C35: 50000 | E35: Устав, п. 3.2
A36: 7 | B36: BAC + ожидаемые потери, USD | C36: =C30+C33 -> 42461 | E36: стр. 1 + стр. 4
A37: 8 | B37: Запас до потолка после ожидаемых потерь, USD | C37: =C35-C36 -> 7539 | E37: стр. 6 − стр. 7
A38: 9 | B38: Фонд времени 19.10–31.12 (68 ч/нед), ч | C38: 720.8 | E38: Книга PERT, лист «Сценарии», вариант Б
A39: 10 | B39: Остаток работ варианта Б, ч | C39: 546.6 | E39: Книга PERT, лист «Сценарии», вариант Б
A40: 11 | B40: Свободный фонд, ч | C40: =C38-C39 -> 174.2 | E40: стр. 9 − стр. 10
A41: 12 | B41: Ожидаемые потери (покрываемые резервом), ч | C41: =G25 -> 141 | E41: итог таблицы выше
A42: 13 | B42: Свободный фонд после ожидаемых потерь, ч | C42: =C40-C41 -> 33.2 | E42: стр. 11 − стр. 12
A44: Вывод: резерв 10% покрывает меньше половины ожидаемых потерь, но вместе с запасом до потолка бюджет держится — BAC с ожидаемыми потерями остаётся ниже 50 000 USD. По времени свободного фонда хватает на ожидаемые потери, однако он распределён неравномерно: дизайнеры и разработчик в ноябре–декабре загружены на 100%, поэтому главные риски по срокам (Р5, Р7, Р12) закрываются мерами и планом Б, а не резервом. Предложение к утверждению базового плана: принять резерв на риски равным сумме ожидаемых потерь (стр. 4) в пределах запаса до потолка — по согласованию с заказчиком (п. 4.2 устава).

Sheet Методика
A1: Методика оценки рисков
A3: Шкала вероятности (P)
A4: Балл | B4: Уровень | C4: Диапазон | D4: Расчётная вероятность | E4: Признаки
A5: 1 | B5: Очень низкая | C5: менее 10% | D5: 0.05 | E5: В похожих учебных проектах не встречалось, есть надёжная защита
A6: 2 | B6: Низкая | C6: 10–30% | D6: 0.2 | E6: Возможно при неблагоприятном стечении обстоятельств
A7: 3 | B7: Средняя | C7: 30–50% | D7: 0.4 | E7: Встречается регулярно; есть предпосылки в данных проекта
A8: 4 | B8: Высокая | C8: 50–70% | D8: 0.6 | E8: Предпосылки уже видны (неподтверждённые допущения, загрузка близка к 100%)
A9: 5 | B9: Очень высокая | C9: более 70% | D9: 0.85 | E9: Почти наверняка произойдёт без мер
A11: Шкала влияния (I) — берётся наихудшее из измерений
A12: Балл | B12: Уровень | C12: Доп. трудозатраты | E12: Сроки | F12: Объём и качество | G12: Стоимость
A13: 1 | B13: Незначительное | C13: менее 8 ч | E13: Вехи не затронуты | F13: Косметические замечания | G13: В пределах полномочий РП, резерв не нужен
A14: 2 | B14: Малое | C14: 8–16 ч | E14: Расходуется до 2 раб. дн запаса (из 5,1) | F14: Замечания по Should / Could | G14: Расход резерва до 1 000 USD (лимит РП на случай)
A15: 3 | B15: Умеренное | C15: 16–40 ч | E15: Расходуется бо́льшая часть запаса; веха на грани | F15: Повторная доработка Must в пределах вехи; под угрозой пакет Should | G15: Расход заметной части резерва 10%
A16: 4 | B16: Значительное | C16: 40–80 ч | E16: Срыв промежуточной вехи | F16: Частичная приёмка вехи; урезание Should | G16: Резерва 10% не хватает, нужен запас до потолка
A17: 5 | B17: Критическое | C17: более 80 ч | E17: Срыв финальной приёмки 26.12 | F17: Не выполняется критерий Must или цель Ц1 / Ц6 | G17: Выход за потолок 50 000 USD
A19: Приоритет: балл = P × I (от 1 до 25)
A20: Приоритет | C20: Балл от | E20: Как работаем с риском
A21: Высокий | C21: 12 | E21: Меры запускаются сразу; риск разбирается на каждой еженедельной синхронизации; статус — в отчёте на демонстрации
A22: Средний | C22: 6 | E22: Меры запланированы в бэклоге; признаки проверяются на каждой демонстрации
A23: Низкий | C23: 1 | E23: Наблюдение; пересмотр при актуализации реестра раз в итерацию
A25: Стратегии реагирования на угрозы
A26: Стратегия | C26: Смысл
A27: Уклонение | C27: Изменить план или границы так, чтобы риск не мог наступить (закрепить границы в уставе, исключить источник).
A28: Передача | C28: Переложить ответственность за последствия на сторону, которая ими управляет (состав полей утверждает заказчик).
A29: Снижение | C29: Уменьшить вероятность и/или влияние превентивными мерами до наступления риска.
A30: Принятие (активное) | C30: Мер до наступления нет или они дороже риска; заложен резерв (время, деньги) и готов план Б.
A31: Эскалация | C31: Решение вне полномочий РП и заказчика — передаётся куратору (п. 4.2 устава).
A33: Порядок составления и оценки
A34: 1. Выявление. Источники рисков: устав, п. 1.5 (риски Р1–Р10, номера сохранены); реестр заинтересованных сторон, столбец «Что из этого следует»; результаты фазы 3 — сетевой график, расписание, сценарии и запрос на изменение № 1 (новые риски Р11–Р17). Источник риска указывается номером стороны из реестра (С-xx).
A35: 2. Описание. Для каждого риска записываются причина и событие, последствия для проекта, связанные пакеты ИСР и требования, признак наступления (наблюдаемый, с датой или порогом из расписания).
A36: 3. Экспертная оценка P и I. Участники независимо ставят баллы по шкалам выше. Если разброс больше 1 балла, авторы крайних оценок и владелец риска объясняют позицию, оценка повторяется. Итог — округлённое среднее, когда разброс сократился до 1 балла. Влияние оценивается по наихудшему из измерений шкалы.
A37: 4. Приоритизация. Балл = P × I; приоритет определяется по порогам выше (пороги — входные ячейки, формулы реестра ссылаются на них).
A38: 5. Количественная оценка. Ожидаемые потери = расчётная вероятность × потери при наступлении (ч) × 55 USD/ч (средняя ставка сводной таблицы оценок). Сумма сравнивается с резервом на риски 10% и свободным фондом времени (лист «Количественная оценка»).
A39: 6. Реагирование. Для каждого риска выбирается стратегия, превентивные меры, план Б на случай наступления и владелец — участник, который следит за признаком и запускает план Б.
A40: 7. Актуализация. Реестр пересматривается на каждой итерации (фазы 5–8): новые риски, сработавшие риски и принятые меры, изменение оценок. Изменения плана по сработавшим рискам — через журнал изменений.
A42: Синим шрифтом выделены входные значения (шкала вероятности, пороги приоритета, оценки P и I, потери в часах) — их можно менять, остальное пересчитывается формулами.
